{"paiva":"2024-06-21","jarjestaja_id":"-306421049","jarjestaja_nimi":"Agility Festivals ry","kilpailu_id":"-1174417070","kilpailu_kuvaus":"D hyppyrata","kilpailu_tyyppi":"1","luokka_koodi":"L3","luokka_kuvaus":"Maksi 3","indeksi":"45","koirakoita":"60","jaljella":"0","ihanneaika":"49","enimmaisaika":"74","pituus":"219","aloitusaika":"13:00","tuomari":"Petr Pup\u00edk (Tsekki)","tulokset":[{"id":255,"indeksi":45,"numero":"461","joukkuenumero":"","jasennumero":"","rotukoodi":"297","rotulyhenne":"borcol","rotunimi":"bordercollie","sukupuoli":"narttu","kutsumanimi":"Ninja","tittelit":"","virallinenNimi":"BE MY NINJA FROM EXTREME TEAM","rekisterinumero":"FI40851/19","syntymaaika":"31.1.2019","ika":"5 v 4 kk 21 pv","ohjaaja":"Sari Johanna Laurikkala","lisenssi":"31938264","seuralyhenne":"JAU","seuranimi":"JÄRVENPÄÄN AGILITYURHEILIJAT RY","joukkue":"","joukkuelyhenne":"","tuloksia":1,"jaljella":"","ihanneaika":"49","enimmaisaika":"74","tavoiteaika":"","suoritusaika":"38,03","nopeus":"5,76","aikavirhe":"-10,97","ratavirhe":0,"perusvirheita":0,"kieltovirheita":1,"pisteet1":"","pisteet2":"","pisteet3":"","pisteet4":"","pisteet5":"","pisteet6":"","pisteet7":"","jokeri":"","miniGamble":"","gamble":"","summa":"","pisteet":"","tulos":"-10,97","sijoitus":1,"muuta":"","naytaMuuta":"","luotu":"2024-06-18T10:42:47.245+0300","riviMuokattu":"2024-06-21T14:09:42.654+0300","tulosMuokattu":"2024-06-21T14:09:42.654+0300"},{"id":274,"indeksi":45,"numero":"469","joukkuenumero":"","jasennumero":"","rotukoodi":"297","rotulyhenne":"borcol","rotunimi":"bordercollie","sukupuoli":"uros","kutsumanimi":"Siks","tittelit":"","virallinenNimi":"EBONY NOSE JACK DANIEL'S","rekisterinumero":"ER53976/17","syntymaaika":"6.5.2017","ika":"7 v 1 kk 15 pv","ohjaaja":"Sanna Rautio","lisenssi":"40282658","seuralyhenne":"LÄGI","seuranimi":"LÄNSI-UUDENMAAN AGILITYHARRASTAJAT","joukkue":"","joukkuelyhenne":"","tuloksia":1,"jaljella":"","ihanneaika":"49","enimmaisaika":"74","tavoiteaika":"","suoritusaika":"38,96","nopeus":"5,62","aikavirhe":"-10,04","ratavirhe":0,"perusvirheita":0,"kieltovirheita":1,"pisteet1":"","pisteet2":"","pisteet3":"","pisteet4":"","pisteet5":"","pisteet6":"","pisteet7":"","jokeri":"","miniGamble":"","gamble":"","summa":"","pisteet":"","tulos":"-10,04","sijoitus":2,"muuta":"","naytaMuuta":"SERT-H","luotu":"2024-06-18T10:42:47.277+0300","riviMuokattu":"2024-06-21T15:02:37.444+0300","tulosMuokattu":"2024-06-21T14:17:23.777+0300"},{"id":283,"indeksi":45,"numero":"427","joukkuenumero":"","jasennumero":"","rotukoodi":"15,4","rotulyhenne":"belpat","rotunimi":"belgianpaimenkoira, tervueren","sukupuoli":"narttu","kutsumanimi":"Ruu","tittelit":"","virallinenNimi":"VALKOHAMPAAN IHMEOTUS","rekisterinumero":"FI37486/18","syntymaaika":"8.6.2018","ika":"6 v 0 kk 13 pv","ohjaaja":"Mikko Naumanen","lisenssi":"22670065","seuralyhenne":"KSSK","seuranimi":"KOUVOLAN SEUDUN SEURAKOIRAKERHO RY","joukkue":"","joukkuelyhenne":"","tuloksia":1,"jaljella":"","ihanneaika":"49","enimmaisaika":"74","tavoiteaika":"","suoritusaika":"39,36","nopeus":"5,56","aikavirhe":"-9,64","ratavirhe":0,"perusvirheita":0,"kieltovirheita":1,"pisteet1":"","pisteet2":"","pisteet3":"","pisteet4":"","pisteet5":"","pisteet6":"","pisteet7":"","jokeri":"","miniGamble":"","gamble":"","summa":"","pisteet":"","tulos":"-9,64","sijoitus":3,"muuta":"","naytaMuuta":"","luotu":"2024-06-18T10:42:47.277+0300","riviMuokattu":"2024-06-21T14:17:23.777+0300","tulosMuokattu":"2024-06-21T13:19:49.281+0300"},{"id":281,"indeksi":45,"numero":"445","joukkuenumero":"","jasennumero":"","rotukoodi":"297","rotulyhenne":"borcol","rotunimi":"bordercollie","sukupuoli":"narttu","kutsumanimi":"Hupi","tittelit":"","virallinenNimi":"SAUNAJAAKON BLUFF","rekisterinumero":"ER26298/17","syntymaaika":"1.4.2017","ika":"7 v 2 kk 20 pv","ohjaaja":"Marjo Korander","lisenssi":"26378680","seuralyhenne":"LÄGI","seuranimi":"LÄNSI-UUDENMAAN AGILITYHARRASTAJAT","joukkue":"","joukkuelyhenne":"","tuloksia":1,"jaljella":"","ihanneaika":"49","enimmaisaika":"74","tavoiteaika":"","suoritusaika":"39,58","nopeus":"5,53","aikavirhe":"-9,42","ratavirhe":0,"perusvirheita":0,"kieltovirheita":1,"pisteet1":"","pisteet2":"","pisteet3":"","pisteet4":"","pisteet5":"","pisteet6":"","pisteet7":"","jokeri":"","miniGamble":"","gamble":"","summa":"","pisteet":"","tulos":"-9,42","sijoitus":4,"muuta":"","naytaMuuta":"","luotu":"2024-06-18T10:42:47.277+0300","riviMuokattu":"2024-06-21T14:17:23.777+0300","tulosMuokattu":"2024-06-21T13:23:40.369+0300"},{"id":302,"indeksi":45,"numero":"455","joukkuenumero":"","jasennumero":"","rotukoodi":"297","rotulyhenne":"borcol","rotunimi":"bordercollie","sukupuoli":"uros","kutsumanimi":"Bou","tittelit":"","virallinenNimi":"LITTLE STEP'S VIVALDI","rekisterinumero":"ER35296/17","syntymaaika":"26.5.2017","ika":"7 v 0 kk 26 pv","ohjaaja":"Tessa Seuranen","lisenssi":"40412946","seuralyhenne":"LÄGI","seuranimi":"LÄNSI-UUDENMAAN AGILITYHARRASTAJAT","joukkue":"","joukkuelyhenne":"","tuloksia":1,"jaljella":"","ihanneaika":"49","enimmaisaika":"74","tavoiteaika":"","suoritusaika":"40,38","nopeus":"5,42","aikavirhe":"-8,62","ratavirhe":0,"perusvirheita":0,"kieltovirheita":1,"pisteet1":"","pisteet2":"","pisteet3":"","pisteet4":"","pisteet5":"","pisteet6":"","pisteet7":"","jokeri":"","miniGamble":"","gamble":"","summa":"","pisteet":"","tulos":"-8,62","sijoitus":5,"muuta":"","naytaMuuta":"","luotu":"2024-06-18T10:42:47.308+0300","riviMuokattu":"2024-06-21T14:17:23.777+0300","tulosMuokattu":"2024-06-21T13:43:20.461+0300"},{"id":298,"indeksi":45,"numero":"437","joukkuenumero":"","jasennumero":"","rotukoodi":"15,1","rotulyhenne":"belpag","rotunimi":"belgianpaimenkoira, groenendael","sukupuoli":"uros","kutsumanimi":"Nude","tittelit":"","virallinenNimi":"VALKOHAMPAAN ILKOSILLAAN","rekisterinumero":"FI37483/18","syntymaaika":"8.6.2018","ika":"6 v 0 kk 13 pv","ohjaaja":"Asko Salmi","lisenssi":"32957891","seuralyhenne":"I-HAH","seuranimi":"ITÄ-HELSINGIN AGILITYHARRASTAJAT RY","joukkue":"","joukkuelyhenne":"","tuloksia":1,"jaljella":"","ihanneaika":"49","enimmaisaika":"74","tavoiteaika":"","suoritusaika":"41,76","nopeus":"5,24","aikavirhe":"-7,24","ratavirhe":0,"perusvirheita":0,"kieltovirheita":1,"pisteet1":"","pisteet2":"","pisteet3":"","pisteet4":"","pisteet5":"","pisteet6":"","pisteet7":"","jokeri":"","miniGamble":"","gamble":"","summa":"","pisteet":"","tulos":"-7,24","sijoitus":6,"muuta":"","naytaMuuta":"","luotu":"2024-06-18T10:42:47.308+0300","riviMuokattu":"2024-06-21T14:17:23.777+0300","tulosMuokattu":"2024-06-21T13:29:55.255+0300"},{"id":295,"indeksi":45,"numero":"472","joukkuenumero":"","jasennumero":"","rotukoodi":"297","rotulyhenne":"borcol","rotunimi":"bordercollie","sukupuoli":"narttu","kutsumanimi":"Toki","tittelit":"","virallinenNimi":"PROMILLEN MALIBU","rekisterinumero":"FI37510/20","syntymaaika":"3.6.2020","ika":"4 v 0 kk 18 pv","ohjaaja":"Tuulia Liuhto","lisenssi":"32192601","seuralyhenne":"LAW","seuranimi":"Littoisten Agility Warriors ry","joukkue":"","joukkuelyhenne":"","tuloksia":1,"jaljella":"","ihanneaika":"49","enimmaisaika":"74","tavoiteaika":"","suoritusaika":"42,78","nopeus":"5,12","aikavirhe":"-6,22","ratavirhe":0,"perusvirheita":0,"kieltovirheita":1,"pisteet1":"","pisteet2":"","pisteet3":"","pisteet4":"","pisteet5":"","pisteet6":"","pisteet7":"","jokeri":"","miniGamble":"","gamble":"","summa":"","pisteet":"","tulos":"-6,22","sijoitus":7,"muuta":"","naytaMuuta":"","luotu":"2024-06-18T10:42:47.292+0300","riviMuokattu":"2024-06-21T15:11:14.195+0300","tulosMuokattu":"2024-06-21T15:11:14.180+0300"},{"id":300,"indeksi":45,"numero":"425","joukkuenumero":"","jasennumero":"","rotukoodi":"166,1","rotulyhenne":"sakpai","rotunimi":"saksanpaimenkoira, pitkäkarvainen","sukupuoli":"narttu","kutsumanimi":"Shiney","tittelit":"","virallinenNimi":"TEAM LEIKSAID OLIVIJA","rekisterinumero":"FI45453/17","syntymaaika":"7.7.2017","ika":"6 v 11 kk 14 pv","ohjaaja":"Kairi Sälik","lisenssi":"40136115","seuralyhenne":"NAS","seuranimi":"NORTHERN AGILITY SPORT RY","joukkue":"","joukkuelyhenne":"","tuloksia":1,"jaljella":"","ihanneaika":"49","enimmaisaika":"74","tavoiteaika":"","suoritusaika":"49,03","nopeus":"4,47","aikavirhe":"0,03","ratavirhe":0,"perusvirheita":0,"kieltovirheita":1,"pisteet1":"","pisteet2":"","pisteet3":"","pisteet4":"","pisteet5":"","pisteet6":"","pisteet7":"","jokeri":"","miniGamble":"","gamble":"","summa":"","pisteet":"","tulos":"0,03","sijoitus":8,"muuta":"","naytaMuuta":"","luotu":"2024-06-18T10:42:47.308+0300","riviMuokattu":"2024-06-21T15:11:14.195+0300","tulosMuokattu":"2024-06-21T13:18:54.874+0300"},{"id":267,"indeksi":45,"numero":"476","joukkuenumero":"","jasennumero":"","rotukoodi":"297","rotulyhenne":"borcol","rotunimi":"bordercollie","sukupuoli":"uros","kutsumanimi":"Kyoto","tittelit":"","virallinenNimi":"Fire Rock Keepgoing","rekisterinumero":"EST-01914/20","syntymaaika":"31.3.2020","ika":"4 v 2 kk 21 pv","ohjaaja":"Kaisa Tamm","lisenssi":"","seuralyhenne":"","seuranimi":"","joukkue":"","joukkuelyhenne":"","tuloksia":1,"jaljella":"","ihanneaika":"49","enimmaisaika":"74","tavoiteaika":"","suoritusaika":"37,68","nopeus":"5,81","aikavirhe":"-11,32","ratavirhe":5,"perusvirheita":1,"kieltovirheita":1,"pisteet1":"","pisteet2":"","pisteet3":"","pisteet4":"","pisteet5":"","pisteet6":"","pisteet7":"","jokeri":"","miniGamble":"","gamble":"","summa":"","pisteet":"","tulos":"5","sijoitus":9,"muuta":"","naytaMuuta":"","luotu":"2024-06-18T10:42:47.261+0300","riviMuokattu":"2024-06-21T15:11:14.195+0300","tulosMuokattu":"2024-06-21T14:26:01.026+0300"},{"id":305,"indeksi":45,"numero":"462","joukkuenumero":"","jasennumero":"","rotukoodi":"293","rotulyhenne":"auskel","rotunimi":"australiankelpie","sukupuoli":"uros","kutsumanimi":"Väinö","tittelit":"","virallinenNimi":"NALLIKALLION KERBEROS","rekisterinumero":"ER51236/20","syntymaaika":"12.9.2020","ika":"3 v 9 kk 9 pv","ohjaaja":"Elisa Rytkönen","lisenssi":"23110456","seuralyhenne":"LAGU","seuranimi":"LAKEUDEN AGILITYURHEILIJAT RY","joukkue":"","joukkuelyhenne":"","tuloksia":1,"jaljella":"","ihanneaika":"49","enimmaisaika":"74","tavoiteaika":"","suoritusaika":"39,55","nopeus":"5,54","aikavirhe":"-9,45","ratavirhe":5,"perusvirheita":1,"kieltovirheita":1,"pisteet1":"","pisteet2":"","pisteet3":"","pisteet4":"","pisteet5":"","pisteet6":"","pisteet7":"","jokeri":"","miniGamble":"","gamble":"","summa":"","pisteet":"","tulos":"5","sijoitus":10,"muuta":"","naytaMuuta":"","luotu":"2024-06-18T10:42:47.308+0300","riviMuokattu":"2024-06-21T15:11:14.195+0300","tulosMuokattu":"2024-06-21T14:10:35.864+0300"},{"id":270,"indeksi":45,"numero":"436","joukkuenumero":"","jasennumero":"","rotukoodi":"296","rotulyhenne":"lyhcol","rotunimi":"sileäkarvainen collie","sukupuoli":"narttu","kutsumanimi":"Ima","tittelit":"","virallinenNimi":"Svagni Leela","rekisterinumero":"RKF 5289590","syntymaaika":"2.4.2018","ika":"6 v 2 kk 19 pv","ohjaaja":"Maria Evstigneeva","lisenssi":"60429376","seuralyhenne":"JAU","seuranimi":"JÄRVENPÄÄN AGILITYURHEILIJAT RY","joukkue":"","joukkuelyhenne":"","tuloksia":1,"jaljella":"","ihanneaika":"49","enimmaisaika":"74","tavoiteaika":"","suoritusaika":"41,80","nopeus":"5,24","aikavirhe":"-7,20","ratavirhe":5,"perusvirheita":1,"kieltovirheita":1,"pisteet1":"","pisteet2":"","pisteet3":"","pisteet4":"","pisteet5":"","pisteet6":"","pisteet7":"","jokeri":"","miniGamble":"","gamble":"","summa":"","pisteet":"","tulos":"5","sijoitus":11,"muuta":"","naytaMuuta":"","luotu":"2024-06-18T10:42:47.273+0300","riviMuokattu":"2024-06-21T15:11:14.211+0300","tulosMuokattu":"2024-06-21T14:12:46.356+0300"},{"id":285,"indeksi":45,"numero":"471","joukkuenumero":"","jasennumero":"","rotukoodi":"297","rotulyhenne":"borcol","rotunimi":"bordercollie","sukupuoli":"narttu","kutsumanimi":"Nike","tittelit":"","virallinenNimi":"EAGLE SPIRIT AWENYA","rekisterinumero":"FI14296/19","syntymaaika":"5.10.2018","ika":"5 v 8 kk 16 pv","ohjaaja":"Heini Lindholm","lisenssi":"22453745","seuralyhenne":"I-HAH","seuranimi":"ITÄ-HELSINGIN AGILITYHARRASTAJAT RY","joukkue":"","joukkuelyhenne":"","tuloksia":1,"jaljella":"","ihanneaika":"49","enimmaisaika":"74","tavoiteaika":"","suoritusaika":"42,04","nopeus":"5,21","aikavirhe":"-6,96","ratavirhe":5,"perusvirheita":1,"kieltovirheita":1,"pisteet1":"","pisteet2":"","pisteet3":"","pisteet4":"","pisteet5":"","pisteet6":"","pisteet7":"","jokeri":"","miniGamble":"","gamble":"","summa":"","pisteet":"","tulos":"5","sijoitus":12,"muuta":"","naytaMuuta":"","luotu":"2024-06-18T10:42:47.292+0300","riviMuokattu":"2024-06-21T15:11:14.211+0300","tulosMuokattu":"2024-06-21T14:21:06.070+0300"},{"id":287,"indeksi":45,"numero":"487","joukkuenumero":"","jasennumero":"","rotukoodi":"297","rotulyhenne":"borcol","rotunimi":"bordercollie","sukupuoli":"narttu","kutsumanimi":"Lin","tittelit":"","virallinenNimi":"Peatdigger Ruby","rekisterinumero":"ER51597/14","syntymaaika":"28.9.2014","ika":"9 v 8 kk 24 pv","ohjaaja":"Anni Kelkka","lisenssi":"40006225","seuralyhenne":"HAU","seuranimi":"HELSINGIN AGILITY URHEILIJAT RY","joukkue":"","joukkuelyhenne":"","tuloksia":1,"jaljella":"","ihanneaika":"49","enimmaisaika":"74","tavoiteaika":"","suoritusaika":"42,84","nopeus":"5,11","aikavirhe":"-6,16","ratavirhe":5,"perusvirheita":0,"kieltovirheita":1,"pisteet1":"","pisteet2":"","pisteet3":"","pisteet4":"","pisteet5":"","pisteet6":"","pisteet7":"","jokeri":"","miniGamble":"","gamble":"","summa":"","pisteet":"","tulos":"5","sijoitus":13,"muuta":"","naytaMuuta":"","luotu":"2024-06-18T10:42:47.292+0300","riviMuokattu":"2024-06-21T14:39:03.216+0300","tulosMuokattu":"2024-06-21T14:39:03.216+0300"},{"id":251,"indeksi":45,"numero":"447","joukkuenumero":"","jasennumero":"","rotukoodi":"297","rotulyhenne":"borcol","rotunimi":"bordercollie","sukupuoli":"uros","kutsumanimi":"Otus","tittelit":"","virallinenNimi":"SUPERMAN","rekisterinumero":"ER52867/20","syntymaaika":"28.9.2020","ika":"3 v 8 kk 24 pv","ohjaaja":"Kati Koto","lisenssi":"27162167","seuralyhenne":"JAT","seuranimi":"JYVÄSKYLÄN AGILITY TEAM RY","joukkue":"","joukkuelyhenne":"","tuloksia":1,"jaljella":"","ihanneaika":"49","enimmaisaika":"74","tavoiteaika":"","suoritusaika":"43,61","nopeus":"5,02","aikavirhe":"-5,39","ratavirhe":5,"perusvirheita":1,"kieltovirheita":1,"pisteet1":"","pisteet2":"","pisteet3":"","pisteet4":"","pisteet5":"","pisteet6":"","pisteet7":"","jokeri":"","miniGamble":"","gamble":"","summa":"","pisteet":"","tulos":"5","sijoitus":14,"muuta":"","naytaMuuta":"","luotu":"2024-06-18T10:42:47.229+0300","riviMuokattu":"2024-06-21T14:39:03.216+0300","tulosMuokattu":"2024-06-21T13:38:49.869+0300"},{"id":291,"indeksi":45,"numero":"457","joukkuenumero":"","jasennumero":"","rotukoodi":"15,4","rotulyhenne":"belpat","rotunimi":"belgianpaimenkoira, tervueren","sukupuoli":"uros","kutsumanimi":"Bartukas","tittelit":"","virallinenNimi":"Bartas Balkūnai","rekisterinumero":"AB-100","syntymaaika":"10.1.2022","ika":"2 v 5 kk 11 pv","ohjaaja":"Jolanta Janušauskienė","lisenssi":"","seuralyhenne":"","seuranimi":"","joukkue":"","joukkuelyhenne":"","tuloksia":1,"jaljella":"","ihanneaika":"49","enimmaisaika":"74","tavoiteaika":"","suoritusaika":"44,15","nopeus":"4,96","aikavirhe":"-4,85","ratavirhe":5,"perusvirheita":0,"kieltovirheita":1,"pisteet1":"","pisteet2":"","pisteet3":"","pisteet4":"","pisteet5":"","pisteet6":"","pisteet7":"","jokeri":"","miniGamble":"","gamble":"","summa":"","pisteet":"","tulos":"5","sijoitus":15,"muuta":"","naytaMuuta":"","luotu":"2024-06-18T10:42:47.292+0300","riviMuokattu":"2024-06-21T14:39:03.216+0300","tulosMuokattu":"2024-06-21T13:45:28.608+0300"},{"id":263,"indeksi":45,"numero":"442","joukkuenumero":"","jasennumero":"","rotukoodi":"297","rotulyhenne":"borcol","rotunimi":"bordercollie","sukupuoli":"uros","kutsumanimi":"Pose","tittelit":"","virallinenNimi":"STRONG SOUND MARVELLOUS MAGNUM","rekisterinumero":"FI59019/21","syntymaaika":"19.10.2021","ika":"2 v 8 kk 2 pv","ohjaaja":"Miisa Rapi","lisenssi":"33120258","seuralyhenne":"LAU","seuranimi":"LAPPEENRANNAN AGILITY URHEILIJAT RY","joukkue":"","joukkuelyhenne":"","tuloksia":1,"jaljella":"","ihanneaika":"49","enimmaisaika":"74","tavoiteaika":"","suoritusaika":"48,63","nopeus":"4,50","aikavirhe":"-0,37","ratavirhe":5,"perusvirheita":0,"kieltovirheita":1,"pisteet1":"","pisteet2":"","pisteet3":"","pisteet4":"","pisteet5":"","pisteet6":"","pisteet7":"","jokeri":"","miniGamble":"","gamble":"","summa":"","pisteet":"","tulos":"5","sijoitus":16,"muuta":"","naytaMuuta":"","luotu":"2024-06-18T10:42:47.261+0300","riviMuokattu":"2024-06-21T14:39:03.216+0300","tulosMuokattu":"2024-06-21T13:34:36.756+0300"},{"id":289,"indeksi":45,"numero":"480","joukkuenumero":"","jasennumero":"","rotukoodi":"212","rotulyhenne":"samoje","rotunimi":"samojedinkoira","sukupuoli":"uros","kutsumanimi":"Mo","tittelit":"","virallinenNimi":"Mazoji loke My Moon Dragon","rekisterinumero":"LŠVK SA 0765/19","syntymaaika":"30.11.2018","ika":"5 v 6 kk 22 pv","ohjaaja":"Violeta  Nomeikienė","lisenssi":"","seuralyhenne":"","seuranimi":"","joukkue":"","joukkuelyhenne":"","tuloksia":1,"jaljella":"","ihanneaika":"49","enimmaisaika":"74","tavoiteaika":"","suoritusaika":"55,22","nopeus":"3,97","aikavirhe":"6,22","ratavirhe":0,"perusvirheita":0,"kieltovirheita":1,"pisteet1":"","pisteet2":"","pisteet3":"","pisteet4":"","pisteet5":"","pisteet6":"","pisteet7":"","jokeri":"","miniGamble":"","gamble":"","summa":"","pisteet":"","tulos":"6,22","sijoitus":17,"muuta":"","naytaMuuta":"","luotu":"2024-06-18T10:42:47.292+0300","riviMuokattu":"2024-06-21T14:39:03.216+0300","tulosMuokattu":"2024-06-21T14:32:41.690+0300"},{"id":294,"indeksi":45,"numero":"463","joukkuenumero":"","jasennumero":"","rotukoodi":"297","rotulyhenne":"borcol","rotunimi":"bordercollie","sukupuoli":"uros","kutsumanimi":"Jorma","tittelit":"","virallinenNimi":"MINDPOWER SUN GO DOWN","rekisterinumero":"FI24680/18","syntymaaika":"6.3.2018","ika":"6 v 3 kk 15 pv","ohjaaja":"Jonna Nevalainen","lisenssi":"27521724","seuralyhenne":"TAMSK","seuranimi":"TAMPEREEN SEUDUN KOIRAKERHO R.Y.","joukkue":"","joukkuelyhenne":"","tuloksia":1,"jaljella":"","ihanneaika":"49","enimmaisaika":"74","tavoiteaika":"","suoritusaika":"37,89","nopeus":"5,78","aikavirhe":"-11,11","ratavirhe":10,"perusvirheita":2,"kieltovirheita":1,"pisteet1":"","pisteet2":"","pisteet3":"","pisteet4":"","pisteet5":"","pisteet6":"","pisteet7":"","jokeri":"","miniGamble":"","gamble":"","summa":"","pisteet":"","tulos":"10","sijoitus":18,"muuta":"","naytaMuuta":"","luotu":"2024-06-18T10:42:47.292+0300","riviMuokattu":"2024-06-21T14:39:03.216+0300","tulosMuokattu":"2024-06-21T13:11:52.993+0300"},{"id":257,"indeksi":45,"numero":"458","joukkuenumero":"","jasennumero":"","rotukoodi":"297","rotulyhenne":"borcol","rotunimi":"bordercollie","sukupuoli":"narttu","kutsumanimi":"Wow","tittelit":"","virallinenNimi":"SHADOW OF AIRE TAKE A CHANCE","rekisterinumero":"ER33835/18","syntymaaika":"18.1.2018","ika":"6 v 5 kk 3 pv","ohjaaja":"Jaakko Suoknuuti","lisenssi":"32123395","seuralyhenne":"LAW","seuranimi":"Littoisten Agility Warriors ry","joukkue":"","joukkuelyhenne":"","tuloksia":1,"jaljella":"","ihanneaika":"49","enimmaisaika":"74","tavoiteaika":"","suoritusaika":"38,09","nopeus":"5,75","aikavirhe":"-10,91","ratavirhe":10,"perusvirheita":2,"kieltovirheita":1,"pisteet1":"","pisteet2":"","pisteet3":"","pisteet4":"","pisteet5":"","pisteet6":"","pisteet7":"","jokeri":"","miniGamble":"","gamble":"","summa":"","pisteet":"","tulos":"10","sijoitus":19,"muuta":"","naytaMuuta":"","luotu":"2024-06-18T10:42:47.245+0300","riviMuokattu":"2024-06-21T14:39:03.228+0300","tulosMuokattu":"2024-06-21T13:46:31.973+0300"},{"id":276,"indeksi":45,"numero":"438","joukkuenumero":"","jasennumero":"","rotukoodi":"297","rotulyhenne":"borcol","rotunimi":"bordercollie","sukupuoli":"uros","kutsumanimi":"Peto","tittelit":"","virallinenNimi":"SOMETHING LIKE NOT YOUR ENEMY","rekisterinumero":"FI10123/20","syntymaaika":"23.11.2019","ika":"4 v 6 kk 29 pv","ohjaaja":"Tiina Leinonen","lisenssi":"26542270","seuralyhenne":"ACTIV","seuranimi":"Active Dogs ry","joukkue":"","joukkuelyhenne":"","tuloksia":1,"jaljella":"","ihanneaika":"49","enimmaisaika":"74","tavoiteaika":"","suoritusaika":"42,83","nopeus":"5,11","aikavirhe":"-6,17","ratavirhe":10,"perusvirheita":1,"kieltovirheita":1,"pisteet1":"","pisteet2":"","pisteet3":"","pisteet4":"","pisteet5":"","pisteet6":"","pisteet7":"","jokeri":"","miniGamble":"","gamble":"","summa":"","pisteet":"","tulos":"10","sijoitus":20,"muuta":"","naytaMuuta":"","luotu":"2024-06-18T10:42:47.277+0300","riviMuokattu":"2024-06-21T14:39:03.228+0300","tulosMuokattu":"2024-06-21T13:31:05.483+0300"},{"id":316,"indeksi":45,"numero":"435","joukkuenumero":"","jasennumero":"","rotukoodi":"297","rotulyhenne":"borcol","rotunimi":"bordercollie","sukupuoli":"uros","kutsumanimi":"Fram","tittelit":"","virallinenNimi":"Follow The Leader For Fire Rock","rekisterinumero":"EST-03661/17","syntymaaika":"18.6.2017","ika":"7 v 0 kk 3 pv","ohjaaja":"Marko Visse","lisenssi":"","seuralyhenne":"","seuranimi":"","joukkue":"","joukkuelyhenne":"","tuloksia":1,"jaljella":"","ihanneaika":"49","enimmaisaika":"74","tavoiteaika":"","suoritusaika":"39,61","nopeus":"5,53","aikavirhe":"-9,39","ratavirhe":15,"perusvirheita":3,"kieltovirheita":1,"pisteet1":"","pisteet2":"","pisteet3":"","pisteet4":"","pisteet5":"","pisteet6":"","pisteet7":"","jokeri":"","miniGamble":"","gamble":"","summa":"","pisteet":"","tulos":"15","sijoitus":21,"muuta":"","naytaMuuta":"","luotu":"2024-06-18T10:42:47.324+0300","riviMuokattu":"2024-06-21T14:39:03.228+0300","tulosMuokattu":"2024-06-21T13:28:45.181+0300"},{"id":312,"indeksi":45,"numero":"478","joukkuenumero":"","jasennumero":"","rotukoodi":"297","rotulyhenne":"borcol","rotunimi":"bordercollie","sukupuoli":"narttu","kutsumanimi":"Kit","tittelit":"","virallinenNimi":"Blessed Borders Significant","rekisterinumero":"DN54150001","syntymaaika":"8.12.2016","ika":"7 v 6 kk 13 pv","ohjaaja":"Jessica Kyle Schumacher","lisenssi":"","seuralyhenne":"","seuranimi":"","joukkue":"","joukkuelyhenne":"","tuloksia":1,"jaljella":"","ihanneaika":"49","enimmaisaika":"74","tavoiteaika":"","suoritusaika":"46,65","nopeus":"4,69","aikavirhe":"-2,35","ratavirhe":15,"perusvirheita":1,"kieltovirheita":1,"pisteet1":"","pisteet2":"","pisteet3":"","pisteet4":"","pisteet5":"","pisteet6":"","pisteet7":"","jokeri":"","miniGamble":"","gamble":"","summa":"","pisteet":"","tulos":"15","sijoitus":22,"muuta":"","naytaMuuta":"","luotu":"2024-06-18T10:42:47.324+0300","riviMuokattu":"2024-06-21T14:39:03.228+0300","tulosMuokattu":"2024-06-21T14:30:00.802+0300"},{"id":247,"indeksi":45,"numero":"475","joukkuenumero":"","jasennumero":"","rotukoodi":"212","rotulyhenne":"samoje","rotunimi":"samojedinkoira","sukupuoli":"narttu","kutsumanimi":"Ice cream","tittelit":"","virallinenNimi":"Amurskaya Zvezda Yagodka Ice Cream","rekisterinumero":"LŠVK SA 1036/22","syntymaaika":"25.9.2021","ika":"2 v 8 kk 27 pv","ohjaaja":"Ieva Nomeikaitė","lisenssi":"","seuralyhenne":"","seuranimi":"","joukkue":"","joukkuelyhenne":"","tuloksia":1,"jaljella":"","ihanneaika":"49","enimmaisaika":"74","tavoiteaika":"","suoritusaika":"56,24","nopeus":"3,89","aikavirhe":"7,24","ratavirhe":15,"perusvirheita":1,"kieltovirheita":1,"pisteet1":"","pisteet2":"","pisteet3":"","pisteet4":"","pisteet5":"","pisteet6":"","pisteet7":"","jokeri":"","miniGamble":"","gamble":"","summa":"","pisteet":"","tulos":"22,24","sijoitus":23,"muuta":"","naytaMuuta":"","luotu":"2024-06-18T10:42:47.229+0300","riviMuokattu":"2024-06-21T14:39:03.228+0300","tulosMuokattu":"2024-06-21T14:24:59.990+0300"},{"id":248,"indeksi":45,"numero":"422","joukkuenumero":"","jasennumero":"","rotukoodi":"297","rotulyhenne":"borcol","rotunimi":"bordercollie","sukupuoli":"uros","kutsumanimi":"Aari","tittelit":"","virallinenNimi":"HAKUKAAREN AARI","rekisterinumero":"ER44241/18","syntymaaika":"7.8.2018","ika":"5 v 10 kk 14 pv","ohjaaja":"Satu Pihlajamäki","lisenssi":"28030081","seuralyhenne":"LÄGI","seuranimi":"LÄNSI-UUDENMAAN AGILITYHARRASTAJAT","joukkue":"","joukkuelyhenne":"","tuloksia":0,"jaljella":"","ihanneaika":"49","enimmaisaika":"74","tavoiteaika":"","suoritusaika":"","nopeus":"","aikavirhe":"","ratavirhe":"","perusvirheita":"","kieltovirheita":0,"pisteet1":"","pisteet2":"","pisteet3":"","pisteet4":"","pisteet5":"","pisteet6":"","pisteet7":"","jokeri":"","miniGamble":"","gamble":"","summa":"","pisteet":"","tulos":"HYL","sijoitus":"","muuta":"","naytaMuuta":"","luotu":"2024-06-18T10:42:47.229+0300","riviMuokattu":"2024-06-21T13:18:52.567+0300","tulosMuokattu":"2024-06-21T13:17:33.092+0300"},{"id":256,"indeksi":45,"numero":"423","joukkuenumero":"","jasennumero":"","rotukoodi":"297","rotulyhenne":"borcol","rotunimi":"bordercollie","sukupuoli":"narttu","kutsumanimi":"Avatar","tittelit":"","virallinenNimi":"HAKUKAAREN AVATAR","rekisterinumero":"ER44234/18","syntymaaika":"7.8.2018","ika":"5 v 10 kk 14 pv","ohjaaja":"Janina Kantola","lisenssi":"32018824","seuralyhenne":"JAT","seuranimi":"JYVÄSKYLÄN AGILITY TEAM RY","joukkue":"","joukkuelyhenne":"","tuloksia":0,"jaljella":"","ihanneaika":"49","enimmaisaika":"74","tavoiteaika":"","suoritusaika":"","nopeus":"","aikavirhe":"","ratavirhe":"","perusvirheita":"","kieltovirheita":0,"pisteet1":"","pisteet2":"","pisteet3":"","pisteet4":"","pisteet5":"","pisteet6":"","pisteet7":"","jokeri":"","miniGamble":"","gamble":"","summa":"","pisteet":"","tulos":"HYL","sijoitus":"","muuta":"","naytaMuuta":"","luotu":"2024-06-18T10:42:47.245+0300","riviMuokattu":"2024-06-21T13:13:18.783+0300","tulosMuokattu":"2024-06-21T13:13:18.775+0300"},{"id":299,"indeksi":45,"numero":"424","joukkuenumero":"","jasennumero":"","rotukoodi":"297","rotulyhenne":"borcol","rotunimi":"bordercollie","sukupuoli":"narttu","kutsumanimi":"Nicsi","tittelit":"","virallinenNimi":"VINDICATE'S PETITE PATCH","rekisterinumero":"FI13264/18","syntymaaika":"12.12.2017","ika":"6 v 6 kk 9 pv","ohjaaja":"Sari Mikkilä","lisenssi":"32131769","seuralyhenne":"LAGU","seuranimi":"LAKEUDEN AGILITYURHEILIJAT RY","joukkue":"","joukkuelyhenne":"","tuloksia":0,"jaljella":"","ihanneaika":"49","enimmaisaika":"74","tavoiteaika":"","suoritusaika":"","nopeus":"","aikavirhe":"","ratavirhe":"","perusvirheita":"","kieltovirheita":0,"pisteet1":"","pisteet2":"","pisteet3":"","pisteet4":"","pisteet5":"","pisteet6":"","pisteet7":"","jokeri":"","miniGamble":"","gamble":"","summa":"","pisteet":"","tulos":"HYL","sijoitus":"","muuta":"","naytaMuuta":"","luotu":"2024-06-18T10:42:47.308+0300","riviMuokattu":"2024-06-21T13:15:39.776+0300","tulosMuokattu":"2024-06-21T13:15:39.776+0300"},{"id":254,"indeksi":45,"numero":"426","joukkuenumero":"","jasennumero":"","rotukoodi":"297","rotulyhenne":"borcol","rotunimi":"bordercollie","sukupuoli":"uros","kutsumanimi":"Naos","tittelit":"","virallinenNimi":"EMPIRE OF FIRE RISING STAR NAOS","rekisterinumero":"FI32380/22","syntymaaika":"27.8.2021","ika":"2 v 9 kk 25 pv","ohjaaja":"Juulia Savolainen","lisenssi":"40242560","seuralyhenne":"KAIKU","seuranimi":"Kaiku agility ry","joukkue":"","joukkuelyhenne":"","tuloksia":0,"jaljella":"","ihanneaika":"49","enimmaisaika":"74","tavoiteaika":"","suoritusaika":"","nopeus":"","aikavirhe":"","ratavirhe":"","perusvirheita":"","kieltovirheita":0,"pisteet1":"","pisteet2":"","pisteet3":"","pisteet4":"","pisteet5":"","pisteet6":"","pisteet7":"","jokeri":"","miniGamble":"","gamble":"","summa":"","pisteet":"","tulos":"HYL","sijoitus":"","muuta":"","naytaMuuta":"","luotu":"2024-06-18T10:42:47.245+0300","riviMuokattu":"2024-06-21T13:14:26.980+0300","tulosMuokattu":"2024-06-21T13:14:26.980+0300"},{"id":296,"indeksi":45,"numero":"428","joukkuenumero":"","jasennumero":"","rotukoodi":"297","rotulyhenne":"borcol","rotunimi":"bordercollie","sukupuoli":"uros","kutsumanimi":"Roy","tittelit":"","virallinenNimi":"SPEAKING BORDERS BOSS","rekisterinumero":"FI11718/21","syntymaaika":"25.11.2019","ika":"4 v 6 kk 27 pv","ohjaaja":"Maria Huttunen","lisenssi":"34334085","seuralyhenne":"JAU","seuranimi":"JÄRVENPÄÄN AGILITYURHEILIJAT RY","joukkue":"","joukkuelyhenne":"","tuloksia":0,"jaljella":"","ihanneaika":"49","enimmaisaika":"74","tavoiteaika":"","suoritusaika":"","nopeus":"","aikavirhe":"","ratavirhe":"","perusvirheita":"","kieltovirheita":0,"pisteet1":"","pisteet2":"","pisteet3":"","pisteet4":"","pisteet5":"","pisteet6":"","pisteet7":"","jokeri":"","miniGamble":"","gamble":"","summa":"","pisteet":"","tulos":"HYL","sijoitus":"","muuta":"","naytaMuuta":"","luotu":"2024-06-18T10:42:47.292+0300","riviMuokattu":"2024-06-21T13:21:22.681+0300","tulosMuokattu":"2024-06-21T13:21:22.681+0300"},{"id":264,"indeksi":45,"numero":"429","joukkuenumero":"","jasennumero":"","rotukoodi":"15,3","rotulyhenne":"belpam","rotunimi":"belgianpaimenkoira, malinois","sukupuoli":"narttu","kutsumanimi":"Sera","tittelit":"","virallinenNimi":"PINKOJAN MORGAN","rekisterinumero":"FI10347/20","syntymaaika":"15.11.2019","ika":"4 v 7 kk 6 pv","ohjaaja":"Miisa Rapi","lisenssi":"33120258","seuralyhenne":"LAU","seuranimi":"LAPPEENRANNAN AGILITY URHEILIJAT RY","joukkue":"","joukkuelyhenne":"","tuloksia":0,"jaljella":"","ihanneaika":"49","enimmaisaika":"74","tavoiteaika":"","suoritusaika":"","nopeus":"","aikavirhe":"","ratavirhe":"","perusvirheita":"","kieltovirheita":0,"pisteet1":"","pisteet2":"","pisteet3":"","pisteet4":"","pisteet5":"","pisteet6":"","pisteet7":"","jokeri":"","miniGamble":"","gamble":"","summa":"","pisteet":"","tulos":"POIS","sijoitus":"","muuta":"","naytaMuuta":"","luotu":"2024-06-18T10:42:47.261+0300","riviMuokattu":"2024-06-21T13:03:15.703+0300","tulosMuokattu":"2024-06-21T13:03:15.688+0300"},{"id":261,"indeksi":45,"numero":"430","joukkuenumero":"","jasennumero":"","rotukoodi":"297","rotulyhenne":"borcol","rotunimi":"bordercollie","sukupuoli":"uros","kutsumanimi":"Kajo","tittelit":"","virallinenNimi":"KAJOSALAMA","rekisterinumero":"ER19967/18","syntymaaika":"23.2.2018","ika":"6 v 3 kk 29 pv","ohjaaja":"Henri Nygren","lisenssi":"33289335","seuralyhenne":"PART","seuranimi":"Pyhäselkä Agility Racing Team Ry","joukkue":"","joukkuelyhenne":"","tuloksia":0,"jaljella":"","ihanneaika":"49","enimmaisaika":"74","tavoiteaika":"","suoritusaika":"","nopeus":"","aikavirhe":"","ratavirhe":"","perusvirheita":"","kieltovirheita":0,"pisteet1":"","pisteet2":"","pisteet3":"","pisteet4":"","pisteet5":"","pisteet6":"","pisteet7":"","jokeri":"","miniGamble":"","gamble":"","summa":"","pisteet":"","tulos":"HYL","sijoitus":"","muuta":"","naytaMuuta":"","luotu":"2024-06-18T10:42:47.245+0300","riviMuokattu":"2024-06-21T13:22:41.370+0300","tulosMuokattu":"2024-06-21T13:22:41.369+0300"},{"id":253,"indeksi":45,"numero":"431","joukkuenumero":"","jasennumero":"","rotukoodi":"297","rotulyhenne":"borcol","rotunimi":"bordercollie","sukupuoli":"uros","kutsumanimi":"Ged","tittelit":"","virallinenNimi":"SAUNAJAAKON ARCHMAGE GED","rekisterinumero":"ER31733/22","syntymaaika":"17.4.2022","ika":"2 v 2 kk 4 pv","ohjaaja":"Marianne Sumela","lisenssi":"32061033","seuralyhenne":"PORSK","seuranimi":"PORVOONSEUDUN KOIRAHARRASTAJAT RY","joukkue":"","joukkuelyhenne":"","tuloksia":0,"jaljella":"","ihanneaika":"49","enimmaisaika":"74","tavoiteaika":"","suoritusaika":"","nopeus":"","aikavirhe":"","ratavirhe":"","perusvirheita":"","kieltovirheita":0,"pisteet1":"","pisteet2":"","pisteet3":"","pisteet4":"","pisteet5":"","pisteet6":"","pisteet7":"","jokeri":"","miniGamble":"","gamble":"","summa":"","pisteet":"","tulos":"HYL","sijoitus":"","muuta":"","naytaMuuta":"","luotu":"2024-06-18T10:42:47.229+0300","riviMuokattu":"2024-06-21T13:24:49.869+0300","tulosMuokattu":"2024-06-21T13:24:49.869+0300"},{"id":279,"indeksi":45,"numero":"432","joukkuenumero":"","jasennumero":"","rotukoodi":"122","rotulyhenne":"labnou","rotunimi":"labradorinnoutaja","sukupuoli":"uros","kutsumanimi":"Hyde","tittelit":"","virallinenNimi":"CAPANDUS IRISH COFFEE","rekisterinumero":"FI38683/19","syntymaaika":"22.4.2019","ika":"5 v 1 kk 30 pv","ohjaaja":"Essi Moring","lisenssi":"60521965","seuralyhenne":"ÅBSK","seuranimi":"ÅLANDS BRUKS- OCH SÄLLSKAPSHUNDSK.","joukkue":"","joukkuelyhenne":"","tuloksia":0,"jaljella":"","ihanneaika":"49","enimmaisaika":"74","tavoiteaika":"","suoritusaika":"","nopeus":"","aikavirhe":"","ratavirhe":"","perusvirheita":"","kieltovirheita":0,"pisteet1":"","pisteet2":"","pisteet3":"","pisteet4":"","pisteet5":"","pisteet6":"","pisteet7":"","jokeri":"","miniGamble":"","gamble":"","summa":"","pisteet":"","tulos":"HYL","sijoitus":"","muuta":"","naytaMuuta":"","luotu":"2024-06-18T10:42:47.277+0300","riviMuokattu":"2024-06-21T13:25:58.946+0300","tulosMuokattu":"2024-06-21T13:25:58.944+0300"},{"id":258,"indeksi":45,"numero":"433","joukkuenumero":"","jasennumero":"","rotukoodi":"15,3","rotulyhenne":"belpam","rotunimi":"belgianpaimenkoira, malinois","sukupuoli":"narttu","kutsumanimi":"Gibli","tittelit":"","virallinenNimi":"KIIRASTULEN DA CAPO","rekisterinumero":"FI32797/17","syntymaaika":"6.5.2017","ika":"7 v 1 kk 15 pv","ohjaaja":"Eeva Pitkänen","lisenssi":"34370890","seuralyhenne":"SBPKY","seuranimi":"Suomen Belgianpaimenkoirayhdistys ry","joukkue":"","joukkuelyhenne":"","tuloksia":0,"jaljella":"","ihanneaika":"49","enimmaisaika":"74","tavoiteaika":"","suoritusaika":"","nopeus":"","aikavirhe":"","ratavirhe":"","perusvirheita":"","kieltovirheita":0,"pisteet1":"","pisteet2":"","pisteet3":"","pisteet4":"","pisteet5":"","pisteet6":"","pisteet7":"","jokeri":"","miniGamble":"","gamble":"","summa":"","pisteet":"","tulos":"POIS","sijoitus":"","muuta":"","naytaMuuta":"","luotu":"2024-06-18T10:42:47.245+0300","riviMuokattu":"2024-06-21T14:48:56.544+0300","tulosMuokattu":"2024-06-21T14:48:56.536+0300"},{"id":250,"indeksi":45,"numero":"434","joukkuenumero":"","jasennumero":"","rotukoodi":"297","rotulyhenne":"borcol","rotunimi":"bordercollie","sukupuoli":"uros","kutsumanimi":"Raa","tittelit":"","virallinenNimi":"SHADOW OF AIRE AMEN","rekisterinumero":"FI58198/21","syntymaaika":"3.11.2020","ika":"3 v 7 kk 18 pv","ohjaaja":"Harri Härkönen","lisenssi":"60417623","seuralyhenne":"TAMSK","seuranimi":"TAMPEREEN SEUDUN KOIRAKERHO R.Y.","joukkue":"","joukkuelyhenne":"","tuloksia":0,"jaljella":"","ihanneaika":"49","enimmaisaika":"74","tavoiteaika":"","suoritusaika":"","nopeus":"","aikavirhe":"","ratavirhe":"","perusvirheita":"","kieltovirheita":0,"pisteet1":"","pisteet2":"","pisteet3":"","pisteet4":"","pisteet5":"","pisteet6":"","pisteet7":"","jokeri":"","miniGamble":"","gamble":"","summa":"","pisteet":"","tulos":"HYL","sijoitus":"","muuta":"","naytaMuuta":"","luotu":"2024-06-18T10:42:47.229+0300","riviMuokattu":"2024-06-21T13:27:48.872+0300","tulosMuokattu":"2024-06-21T13:27:48.872+0300"},{"id":314,"indeksi":45,"numero":"439","joukkuenumero":"","jasennumero":"","rotukoodi":"297","rotulyhenne":"borcol","rotunimi":"bordercollie","sukupuoli":"uros","kutsumanimi":"Abel","tittelit":"","virallinenNimi":"Abel","rekisterinumero":"944116000008674","syntymaaika":"24.11.2020","ika":"3 v 6 kk 28 pv","ohjaaja":"Karina Zarzecka","lisenssi":"","seuralyhenne":"","seuranimi":"","joukkue":"","joukkuelyhenne":"","tuloksia":0,"jaljella":"","ihanneaika":"49","enimmaisaika":"74","tavoiteaika":"","suoritusaika":"","nopeus":"","aikavirhe":"","ratavirhe":"","perusvirheita":"","kieltovirheita":0,"pisteet1":"","pisteet2":"","pisteet3":"","pisteet4":"","pisteet5":"","pisteet6":"","pisteet7":"","jokeri":"","miniGamble":"","gamble":"","summa":"","pisteet":"","tulos":"HYL","sijoitus":"","muuta":"","naytaMuuta":"","luotu":"2024-06-18T10:42:47.324+0300","riviMuokattu":"2024-06-21T13:32:18.176+0300","tulosMuokattu":"2024-06-21T13:32:18.172+0300"},{"id":282,"indeksi":45,"numero":"440","joukkuenumero":"","jasennumero":"","rotukoodi":"297","rotulyhenne":"borcol","rotunimi":"bordercollie","sukupuoli":"uros","kutsumanimi":"Max","tittelit":"","virallinenNimi":"TYH MAX","rekisterinumero":"FI20206/20","syntymaaika":"29.10.2019","ika":"4 v 7 kk 23 pv","ohjaaja":"Tanja Lehto","lisenssi":"24769314","seuralyhenne":"HU-PU","seuranimi":"HUKKA-PUTKI RY","joukkue":"","joukkuelyhenne":"","tuloksia":0,"jaljella":"","ihanneaika":"49","enimmaisaika":"74","tavoiteaika":"","suoritusaika":"","nopeus":"","aikavirhe":"","ratavirhe":"","perusvirheita":"","kieltovirheita":0,"pisteet1":"","pisteet2":"","pisteet3":"","pisteet4":"","pisteet5":"","pisteet6":"","pisteet7":"","jokeri":"","miniGamble":"","gamble":"","summa":"","pisteet":"","tulos":"HYL","sijoitus":"","muuta":"","naytaMuuta":"","luotu":"2024-06-18T10:42:47.277+0300","riviMuokattu":"2024-06-21T13:32:59.370+0300","tulosMuokattu":"2024-06-21T13:32:59.370+0300"},{"id":301,"indeksi":45,"numero":"441","joukkuenumero":"","jasennumero":"","rotukoodi":"297","rotulyhenne":"borcol","rotunimi":"bordercollie","sukupuoli":"uros","kutsumanimi":"Jari","tittelit":"","virallinenNimi":"KHAOS OF QUICK ANGEL","rekisterinumero":"Er41393/19","syntymaaika":"29.7.2018","ika":"5 v 10 kk 23 pv","ohjaaja":"Laura Sutinen","lisenssi":"24234276","seuralyhenne":"HU-PU","seuranimi":"HUKKA-PUTKI RY","joukkue":"","joukkuelyhenne":"","tuloksia":0,"jaljella":"","ihanneaika":"49","enimmaisaika":"74","tavoiteaika":"","suoritusaika":"","nopeus":"","aikavirhe":"","ratavirhe":"","perusvirheita":"","kieltovirheita":0,"pisteet1":"","pisteet2":"","pisteet3":"","pisteet4":"","pisteet5":"","pisteet6":"","pisteet7":"","jokeri":"","miniGamble":"","gamble":"","summa":"","pisteet":"","tulos":"POIS","sijoitus":"","muuta":"","naytaMuuta":"","luotu":"2024-06-18T10:42:47.308+0300","riviMuokattu":"2024-06-21T13:33:05.402+0300","tulosMuokattu":"2024-06-21T13:33:05.402+0300"},{"id":266,"indeksi":45,"numero":"443","joukkuenumero":"","jasennumero":"","rotukoodi":"15,4","rotulyhenne":"belpat","rotunimi":"belgianpaimenkoira, tervueren","sukupuoli":"narttu","kutsumanimi":"Nästi","tittelit":"","virallinenNimi":"VALKOHAMPAAN IHAN NAKUNA","rekisterinumero":"FI37484/18","syntymaaika":"8.6.2018","ika":"6 v 0 kk 13 pv","ohjaaja":"Sara Malinen","lisenssi":"33774905","seuralyhenne":"HSKH","seuranimi":"HAKUNILAN SEUDUN KOIRAHARRASTAJAT","joukkue":"","joukkuelyhenne":"","tuloksia":0,"jaljella":"","ihanneaika":"49","enimmaisaika":"74","tavoiteaika":"","suoritusaika":"","nopeus":"","aikavirhe":"","ratavirhe":"","perusvirheita":"","kieltovirheita":0,"pisteet1":"","pisteet2":"","pisteet3":"","pisteet4":"","pisteet5":"","pisteet6":"","pisteet7":"","jokeri":"","miniGamble":"","gamble":"","summa":"","pisteet":"","tulos":"HYL","sijoitus":"","muuta":"","naytaMuuta":"","luotu":"2024-06-18T10:42:47.261+0300","riviMuokattu":"2024-06-21T13:35:38.699+0300","tulosMuokattu":"2024-06-21T13:35:38.694+0300"},{"id":315,"indeksi":45,"numero":"444","joukkuenumero":"","jasennumero":"","rotukoodi":"297","rotulyhenne":"borcol","rotunimi":"bordercollie","sukupuoli":"narttu","kutsumanimi":"QUEEN AMIDALA, \"AMI\"","tittelit":"","virallinenNimi":"FIRE INSPIRED MAGMA","rekisterinumero":"REGV1622/2020","syntymaaika":"11.3.2019","ika":"5 v 3 kk 10 pv","ohjaaja":"Jouni Orenius","lisenssi":"","seuralyhenne":"","seuranimi":"","joukkue":"","joukkuelyhenne":"","tuloksia":0,"jaljella":"","ihanneaika":"49","enimmaisaika":"74","tavoiteaika":"","suoritusaika":"","nopeus":"","aikavirhe":"","ratavirhe":"","perusvirheita":1,"kieltovirheita":0,"pisteet1":"","pisteet2":"","pisteet3":"","pisteet4":"","pisteet5":"","pisteet6":"","pisteet7":"","jokeri":"","miniGamble":"","gamble":"","summa":"","pisteet":"","tulos":"HYL","sijoitus":"","muuta":"","naytaMuuta":"","luotu":"2024-06-18T10:42:47.324+0300","riviMuokattu":"2024-06-21T13:37:36.922+0300","tulosMuokattu":"2024-06-21T13:37:36.911+0300"},{"id":277,"indeksi":45,"numero":"446","joukkuenumero":"","jasennumero":"","rotukoodi":"297","rotulyhenne":"borcol","rotunimi":"bordercollie","sukupuoli":"uros","kutsumanimi":"Nikka","tittelit":"","virallinenNimi":"PROMILLEN MACALLAN","rekisterinumero":"FI37514/20","syntymaaika":"3.6.2020","ika":"4 v 0 kk 18 pv","ohjaaja":"Timo Liuhto","lisenssi":"22438605","seuralyhenne":"EAC","seuranimi":"Espoo Agility Club ry","joukkue":"","joukkuelyhenne":"","tuloksia":0,"jaljella":"","ihanneaika":"49","enimmaisaika":"74","tavoiteaika":"","suoritusaika":"","nopeus":"","aikavirhe":"","ratavirhe":"","perusvirheita":"","kieltovirheita":0,"pisteet1":"","pisteet2":"","pisteet3":"","pisteet4":"","pisteet5":"","pisteet6":"","pisteet7":"","jokeri":"","miniGamble":"","gamble":"","summa":"","pisteet":"","tulos":"POIS","sijoitus":"","muuta":"","naytaMuuta":"","luotu":"2024-06-18T10:42:47.277+0300","riviMuokattu":"2024-06-21T13:15:25.739+0300","tulosMuokattu":"2024-06-21T12:56:07.425+0300"},{"id":309,"indeksi":45,"numero":"448","joukkuenumero":"","jasennumero":"","rotukoodi":"297","rotulyhenne":"borcol","rotunimi":"bordercollie","sukupuoli":"narttu","kutsumanimi":"Peppi","tittelit":"","virallinenNimi":"GJERULFF WONDERFUL WILLOW GOT THE JACKPOT","rekisterinumero":"FI42444/20","syntymaaika":"1.2.2020","ika":"4 v 4 kk 20 pv","ohjaaja":"Raisa Vähätalo","lisenssi":"32095821","seuralyhenne":"JAU","seuranimi":"JÄRVENPÄÄN AGILITYURHEILIJAT RY","joukkue":"","joukkuelyhenne":"","tuloksia":0,"jaljella":"","ihanneaika":"49","enimmaisaika":"74","tavoiteaika":"","suoritusaika":"","nopeus":"","aikavirhe":"","ratavirhe":"","perusvirheita":"","kieltovirheita":0,"pisteet1":"","pisteet2":"","pisteet3":"","pisteet4":"","pisteet5":"","pisteet6":"","pisteet7":"","jokeri":"","miniGamble":"","gamble":"","summa":"","pisteet":"","tulos":"HYL","sijoitus":"","muuta":"","naytaMuuta":"","luotu":"2024-06-18T10:42:47.324+0300","riviMuokattu":"2024-06-21T14:18:26.250+0300","tulosMuokattu":"2024-06-21T14:18:26.250+0300"},{"id":271,"indeksi":45,"numero":"449","joukkuenumero":"","jasennumero":"","rotukoodi":"297","rotulyhenne":"borcol","rotunimi":"bordercollie","sukupuoli":"narttu","kutsumanimi":"Noli","tittelit":"","virallinenNimi":"PROMILLEN JERSEY DEVIL","rekisterinumero":"ER12898/18","syntymaaika":"10.12.2017","ika":"6 v 6 kk 11 pv","ohjaaja":"Anna Parviainen","lisenssi":"32313419","seuralyhenne":"STAR","seuranimi":"STAR TEAM YLÖJÄRVI RY","joukkue":"","joukkuelyhenne":"","tuloksia":0,"jaljella":"","ihanneaika":"49","enimmaisaika":"74","tavoiteaika":"","suoritusaika":"","nopeus":"","aikavirhe":"","ratavirhe":"","perusvirheita":"","kieltovirheita":0,"pisteet1":"","pisteet2":"","pisteet3":"","pisteet4":"","pisteet5":"","pisteet6":"","pisteet7":"","jokeri":"","miniGamble":"","gamble":"","summa":"","pisteet":"","tulos":"HYL","sijoitus":"","muuta":"","naytaMuuta":"","luotu":"2024-06-18T10:42:47.273+0300","riviMuokattu":"2024-06-21T13:36:39.789+0300","tulosMuokattu":"2024-06-21T13:36:39.787+0300"},{"id":249,"indeksi":45,"numero":"450","joukkuenumero":"","jasennumero":"","rotukoodi":"297","rotulyhenne":"borcol","rotunimi":"bordercollie","sukupuoli":"narttu","kutsumanimi":"Vette","tittelit":"","virallinenNimi":"PROMILLEN JOY JUMPER","rekisterinumero":"ER12900/18","syntymaaika":"10.12.2017","ika":"6 v 6 kk 11 pv","ohjaaja":"Päivi Männistö-Rahunen","lisenssi":"32111064","seuralyhenne":"PIRKU","seuranimi":"PIRKU RY","joukkue":"","joukkuelyhenne":"","tuloksia":0,"jaljella":"","ihanneaika":"49","enimmaisaika":"74","tavoiteaika":"","suoritusaika":"","nopeus":"","aikavirhe":"","ratavirhe":"","perusvirheita":"","kieltovirheita":0,"pisteet1":"","pisteet2":"","pisteet3":"","pisteet4":"","pisteet5":"","pisteet6":"","pisteet7":"","jokeri":"","miniGamble":"","gamble":"","summa":"","pisteet":"","tulos":"HYL","sijoitus":"","muuta":"","naytaMuuta":"","luotu":"2024-06-18T10:42:47.229+0300","riviMuokattu":"2024-06-21T14:28:56.278+0300","tulosMuokattu":"2024-06-21T14:28:56.278+0300"},{"id":303,"indeksi":45,"numero":"451","joukkuenumero":"","jasennumero":"","rotukoodi":"297","rotulyhenne":"borcol","rotunimi":"bordercollie","sukupuoli":"narttu","kutsumanimi":"Siri","tittelit":"","virallinenNimi":"KERTAKAIKKIAAN TÄTÄ TOUHUA","rekisterinumero":"ER22402/21","syntymaaika":"24.2.2021","ika":"3 v 3 kk 28 pv","ohjaaja":"Emma Hiilesniemi","lisenssi":"60289720","seuralyhenne":"JAU","seuranimi":"JÄRVENPÄÄN AGILITYURHEILIJAT RY","joukkue":"","joukkuelyhenne":"","tuloksia":0,"jaljella":"","ihanneaika":"49","enimmaisaika":"74","tavoiteaika":"","suoritusaika":"","nopeus":"","aikavirhe":"","ratavirhe":"","perusvirheita":"","kieltovirheita":0,"pisteet1":"","pisteet2":"","pisteet3":"","pisteet4":"","pisteet5":"","pisteet6":"","pisteet7":"","jokeri":"","miniGamble":"","gamble":"","summa":"","pisteet":"","tulos":"HYL","sijoitus":"","muuta":"","naytaMuuta":"","luotu":"2024-06-18T10:42:47.308+0300","riviMuokattu":"2024-06-21T13:40:24.492+0300","tulosMuokattu":"2024-06-21T13:40:24.492+0300"},{"id":307,"indeksi":45,"numero":"452","joukkuenumero":"","jasennumero":"","rotukoodi":"15,1","rotulyhenne":"belpag","rotunimi":"belgianpaimenkoira, groenendael","sukupuoli":"uros","kutsumanimi":"Shango","tittelit":"","virallinenNimi":"BE'SHANGO BALKŪNAI","rekisterinumero":"AB-97","syntymaaika":"10.1.2022","ika":"2 v 5 kk 11 pv","ohjaaja":"Vaida Silviene","lisenssi":"","seuralyhenne":"","seuranimi":"","joukkue":"","joukkuelyhenne":"","tuloksia":0,"jaljella":"","ihanneaika":"49","enimmaisaika":"74","tavoiteaika":"","suoritusaika":"","nopeus":"","aikavirhe":"","ratavirhe":"","perusvirheita":"","kieltovirheita":0,"pisteet1":"","pisteet2":"","pisteet3":"","pisteet4":"","pisteet5":"","pisteet6":"","pisteet7":"","jokeri":"","miniGamble":"","gamble":"","summa":"","pisteet":"","tulos":"POIS","sijoitus":"","muuta":"","naytaMuuta":"","luotu":"2024-06-18T10:42:47.308+0300","riviMuokattu":"2024-06-21T14:49:00.824+0300","tulosMuokattu":"2024-06-21T14:49:00.824+0300"},{"id":290,"indeksi":45,"numero":"453","joukkuenumero":"","jasennumero":"","rotukoodi":"297","rotulyhenne":"borcol","rotunimi":"bordercollie","sukupuoli":"uros","kutsumanimi":"Ykä","tittelit":"","virallinenNimi":"PROMILLEN ISOKAATO","rekisterinumero":"FI54213/17","syntymaaika":"19.10.2017","ika":"6 v 8 kk 2 pv","ohjaaja":"Sari Vähäniitty","lisenssi":"27269895","seuralyhenne":"PART","seuranimi":"Pyhäselkä Agility Racing Team Ry","joukkue":"","joukkuelyhenne":"","tuloksia":0,"jaljella":"","ihanneaika":"49","enimmaisaika":"74","tavoiteaika":"","suoritusaika":"","nopeus":"","aikavirhe":"","ratavirhe":"","perusvirheita":"","kieltovirheita":0,"pisteet1":"","pisteet2":"","pisteet3":"","pisteet4":"","pisteet5":"","pisteet6":"","pisteet7":"","jokeri":"","miniGamble":"","gamble":"","summa":"","pisteet":"","tulos":"POIS","sijoitus":"","muuta":"","naytaMuuta":"","luotu":"2024-06-18T10:42:47.292+0300","riviMuokattu":"2024-06-21T14:49:04.669+0300","tulosMuokattu":"2024-06-21T14:49:04.668+0300"},{"id":252,"indeksi":45,"numero":"454","joukkuenumero":"","jasennumero":"","rotukoodi":"297","rotulyhenne":"borcol","rotunimi":"bordercollie","sukupuoli":"narttu","kutsumanimi":"Winnie","tittelit":"","virallinenNimi":"MYYTIN MURTUMISPISTE","rekisterinumero":"FI37558/17","syntymaaika":"7.6.2017","ika":"7 v 0 kk 14 pv","ohjaaja":"Jessica Pollari","lisenssi":"60486895","seuralyhenne":"BTW Agility","seuranimi":"Blind To Wrap Agility ry","joukkue":"","joukkuelyhenne":"","tuloksia":0,"jaljella":"","ihanneaika":"49","enimmaisaika":"74","tavoiteaika":"","suoritusaika":"","nopeus":"","aikavirhe":"","ratavirhe":"","perusvirheita":"","kieltovirheita":0,"pisteet1":"","pisteet2":"","pisteet3":"","pisteet4":"","pisteet5":"","pisteet6":"","pisteet7":"","jokeri":"","miniGamble":"","gamble":"","summa":"","pisteet":"","tulos":"HYL","sijoitus":"","muuta":"","naytaMuuta":"","luotu":"2024-06-18T10:42:47.229+0300","riviMuokattu":"2024-06-21T13:42:01.674+0300","tulosMuokattu":"2024-06-21T13:42:01.674+0300"},{"id":273,"indeksi":45,"numero":"456","joukkuenumero":"","jasennumero":"","rotukoodi":"297","rotulyhenne":"borcol","rotunimi":"bordercollie","sukupuoli":"uros","kutsumanimi":"Polar","tittelit":"","virallinenNimi":"SAUNAJAAKON HOAX","rekisterinumero":"ER26294/17","syntymaaika":"1.4.2017","ika":"7 v 2 kk 20 pv","ohjaaja":"Maiju Korhonen","lisenssi":"32134999","seuralyhenne":"HAU","seuranimi":"HELSINGIN AGILITY URHEILIJAT RY","joukkue":"","joukkuelyhenne":"","tuloksia":0,"jaljella":"","ihanneaika":"49","enimmaisaika":"74","tavoiteaika":"","suoritusaika":"","nopeus":"","aikavirhe":"","ratavirhe":"","perusvirheita":"","kieltovirheita":0,"pisteet1":"","pisteet2":"","pisteet3":"","pisteet4":"","pisteet5":"","pisteet6":"","pisteet7":"","jokeri":"","miniGamble":"","gamble":"","summa":"","pisteet":"","tulos":"HYL","sijoitus":"","muuta":"","naytaMuuta":"","luotu":"2024-06-18T10:42:47.277+0300","riviMuokattu":"2024-06-21T13:44:27.680+0300","tulosMuokattu":"2024-06-21T13:44:27.680+0300"},{"id":293,"indeksi":45,"numero":"459","joukkuenumero":"","jasennumero":"","rotukoodi":"297","rotulyhenne":"borcol","rotunimi":"bordercollie","sukupuoli":"uros","kutsumanimi":"COFFEE","tittelit":"","virallinenNimi":"FLYLAND COFFEE WITH MILK","rekisterinumero":"LV-38870/16","syntymaaika":"16.4.2016","ika":"8 v 2 kk 5 pv","ohjaaja":"Julija Kampuse","lisenssi":"","seuralyhenne":"","seuranimi":"","joukkue":"","joukkuelyhenne":"","tuloksia":0,"jaljella":"","ihanneaika":"49","enimmaisaika":"74","tavoiteaika":"","suoritusaika":"","nopeus":"","aikavirhe":"","ratavirhe":"","perusvirheita":"","kieltovirheita":0,"pisteet1":"","pisteet2":"","pisteet3":"","pisteet4":"","pisteet5":"","pisteet6":"","pisteet7":"","jokeri":"","miniGamble":"","gamble":"","summa":"","pisteet":"","tulos":"POIS","sijoitus":"","muuta":"","naytaMuuta":"","luotu":"2024-06-18T10:42:47.292+0300","riviMuokattu":"2024-06-21T14:49:08.635+0300","tulosMuokattu":"2024-06-21T14:49:08.635+0300"},{"id":288,"indeksi":45,"numero":"460","joukkuenumero":"","jasennumero":"","rotukoodi":"297","rotulyhenne":"borcol","rotunimi":"bordercollie","sukupuoli":"narttu","kutsumanimi":"Maj-Lis","tittelit":"","virallinenNimi":"OVERDO TWIST","rekisterinumero":"ER18514/17","syntymaaika":"11.2.2017","ika":"7 v 4 kk 10 pv","ohjaaja":"Maija Anttolainen","lisenssi":"40141770","seuralyhenne":"KAG","seuranimi":"Kaakon Agility Klubi ry","joukkue":"","joukkuelyhenne":"","tuloksia":0,"jaljella":"","ihanneaika":"49","enimmaisaika":"74","tavoiteaika":"","suoritusaika":"","nopeus":"","aikavirhe":"","ratavirhe":"","perusvirheita":"","kieltovirheita":0,"pisteet1":"","pisteet2":"","pisteet3":"","pisteet4":"","pisteet5":"","pisteet6":"","pisteet7":"","jokeri":"","miniGamble":"","gamble":"","summa":"","pisteet":"","tulos":"HYL","sijoitus":"","muuta":"","naytaMuuta":"","luotu":"2024-06-18T10:42:47.292+0300","riviMuokattu":"2024-06-21T13:47:45.062+0300","tulosMuokattu":"2024-06-21T13:47:45.062+0300"},{"id":313,"indeksi":45,"numero":"464","joukkuenumero":"","jasennumero":"","rotukoodi":"297","rotulyhenne":"borcol","rotunimi":"bordercollie","sukupuoli":"uros","kutsumanimi":"Lore","tittelit":"","virallinenNimi":"Tonglen Lake's Way of the Mandalore","rekisterinumero":"AKC DN64005703","syntymaaika":"22.8.2020","ika":"3 v 9 kk 30 pv","ohjaaja":"Kara Sheerer","lisenssi":"","seuralyhenne":"","seuranimi":"","joukkue":"","joukkuelyhenne":"","tuloksia":0,"jaljella":"","ihanneaika":"49","enimmaisaika":"74","tavoiteaika":"","suoritusaika":"","nopeus":"","aikavirhe":"","ratavirhe":"","perusvirheita":"","kieltovirheita":0,"pisteet1":"","pisteet2":"","pisteet3":"","pisteet4":"","pisteet5":"","pisteet6":"","pisteet7":"","jokeri":"","miniGamble":"","gamble":"","summa":"","pisteet":"","tulos":"POIS","sijoitus":"","muuta":"","naytaMuuta":"","luotu":"2024-06-18T10:42:47.324+0300","riviMuokattu":"2024-06-21T14:48:50.146+0300","tulosMuokattu":"2024-06-21T14:48:50.130+0300"},{"id":311,"indeksi":45,"numero":"465","joukkuenumero":"","jasennumero":"","rotukoodi":"297","rotulyhenne":"borcol","rotunimi":"bordercollie","sukupuoli":"uros","kutsumanimi":"Logan","tittelit":"","virallinenNimi":"Borderlands Adamantium","rekisterinumero":"DN62380301","syntymaaika":"8.3.2020","ika":"4 v 3 kk 13 pv","ohjaaja":"Jessica Kyle Schumacher","lisenssi":"","seuralyhenne":"","seuranimi":"","joukkue":"","joukkuelyhenne":"","tuloksia":0,"jaljella":"","ihanneaika":"49","enimmaisaika":"74","tavoiteaika":"","suoritusaika":"","nopeus":"","aikavirhe":"","ratavirhe":"","perusvirheita":"","kieltovirheita":0,"pisteet1":"","pisteet2":"","pisteet3":"","pisteet4":"","pisteet5":"","pisteet6":"","pisteet7":"","jokeri":"","miniGamble":"","gamble":"","summa":"","pisteet":"","tulos":"HYL","sijoitus":"","muuta":"","naytaMuuta":"","luotu":"2024-06-18T10:42:47.324+0300","riviMuokattu":"2024-06-21T14:14:11.294+0300","tulosMuokattu":"2024-06-21T14:14:11.294+0300"},{"id":304,"indeksi":45,"numero":"466","joukkuenumero":"","jasennumero":"","rotukoodi":"297","rotulyhenne":"borcol","rotunimi":"bordercollie","sukupuoli":"narttu","kutsumanimi":"Una","tittelit":"","virallinenNimi":"BROOKE THE MAZE RUNNER","rekisterinumero":"ER38005/21","syntymaaika":"5.11.2019","ika":"4 v 7 kk 16 pv","ohjaaja":"Tiina Sköönilä","lisenssi":"40359274","seuralyhenne":"JAU","seuranimi":"JÄRVENPÄÄN AGILITYURHEILIJAT RY","joukkue":"","joukkuelyhenne":"","tuloksia":0,"jaljella":"","ihanneaika":"49","enimmaisaika":"74","tavoiteaika":"","suoritusaika":"","nopeus":"","aikavirhe":"","ratavirhe":"","perusvirheita":"","kieltovirheita":0,"pisteet1":"","pisteet2":"","pisteet3":"","pisteet4":"","pisteet5":"","pisteet6":"","pisteet7":"","jokeri":"","miniGamble":"","gamble":"","summa":"","pisteet":"","tulos":"HYL","sijoitus":"","muuta":"","naytaMuuta":"","luotu":"2024-06-18T10:42:47.308+0300","riviMuokattu":"2024-06-21T14:15:15.139+0300","tulosMuokattu":"2024-06-21T14:15:15.139+0300"},{"id":280,"indeksi":45,"numero":"467","joukkuenumero":"","jasennumero":"","rotukoodi":"297","rotulyhenne":"borcol","rotunimi":"bordercollie","sukupuoli":"uros","kutsumanimi":"Manuel","tittelit":"","virallinenNimi":"MIND THE DOG CEREBRO","rekisterinumero":"FI15120/22","syntymaaika":"13.5.2021","ika":"3 v 1 kk 8 pv","ohjaaja":"Tuomas Haverila","lisenssi":"27953978","seuralyhenne":"JoA","seuranimi":"JOENSUUN AGILITYURHEILIJAT","joukkue":"","joukkuelyhenne":"","tuloksia":0,"jaljella":"","ihanneaika":"49","enimmaisaika":"74","tavoiteaika":"","suoritusaika":"","nopeus":"","aikavirhe":"","ratavirhe":"","perusvirheita":"","kieltovirheita":0,"pisteet1":"","pisteet2":"","pisteet3":"","pisteet4":"","pisteet5":"","pisteet6":"","pisteet7":"","jokeri":"","miniGamble":"","gamble":"","summa":"","pisteet":"","tulos":"POIS","sijoitus":"","muuta":"","naytaMuuta":"","luotu":"2024-06-18T10:42:47.277+0300","riviMuokattu":"2024-06-21T13:58:52.658+0300","tulosMuokattu":"2024-06-21T13:58:52.647+0300"},{"id":286,"indeksi":45,"numero":"468","joukkuenumero":"","jasennumero":"","rotukoodi":"297","rotulyhenne":"borcol","rotunimi":"bordercollie","sukupuoli":"narttu","kutsumanimi":"Kaneli","tittelit":"","virallinenNimi":"LUMOUS","rekisterinumero":"ER47444/19","syntymaaika":"4.9.2019","ika":"4 v 9 kk 17 pv","ohjaaja":"Anni Kelkka","lisenssi":"40006225","seuralyhenne":"HAU","seuranimi":"HELSINGIN AGILITY URHEILIJAT RY","joukkue":"","joukkuelyhenne":"","tuloksia":0,"jaljella":"","ihanneaika":"49","enimmaisaika":"74","tavoiteaika":"","suoritusaika":"","nopeus":"","aikavirhe":"","ratavirhe":"","perusvirheita":2,"kieltovirheita":0,"pisteet1":"","pisteet2":"","pisteet3":"","pisteet4":"","pisteet5":"","pisteet6":"","pisteet7":"","jokeri":"","miniGamble":"","gamble":"","summa":"","pisteet":"","tulos":"HYL","sijoitus":"","muuta":"","naytaMuuta":"","luotu":"2024-06-18T10:42:47.292+0300","riviMuokattu":"2024-06-21T14:16:26.980+0300","tulosMuokattu":"2024-06-21T14:16:26.977+0300"},{"id":306,"indeksi":45,"numero":"470","joukkuenumero":"","jasennumero":"","rotukoodi":"297","rotulyhenne":"borcol","rotunimi":"bordercollie","sukupuoli":"uros","kutsumanimi":"Code","tittelit":"","virallinenNimi":"QUICK STAR COOLEST TIGER JACK","rekisterinumero":"FI15507/20","syntymaaika":"5.1.2020","ika":"4 v 5 kk 16 pv","ohjaaja":"Susanna Niiranen","lisenssi":"32171350","seuralyhenne":"KirKe","seuranimi":"KIRKKONUMMEN KENNELKERHO RY","joukkue":"","joukkuelyhenne":"","tuloksia":0,"jaljella":"","ihanneaika":"49","enimmaisaika":"74","tavoiteaika":"","suoritusaika":"","nopeus":"","aikavirhe":"","ratavirhe":"","perusvirheita":"","kieltovirheita":0,"pisteet1":"","pisteet2":"","pisteet3":"","pisteet4":"","pisteet5":"","pisteet6":"","pisteet7":"","jokeri":"","miniGamble":"","gamble":"","summa":"","pisteet":"","tulos":"HYL","sijoitus":"","muuta":"","naytaMuuta":"","luotu":"2024-06-18T10:42:47.308+0300","riviMuokattu":"2024-06-21T14:20:01.461+0300","tulosMuokattu":"2024-06-21T14:20:01.461+0300"},{"id":262,"indeksi":45,"numero":"473","joukkuenumero":"","jasennumero":"","rotukoodi":"297","rotulyhenne":"borcol","rotunimi":"bordercollie","sukupuoli":"narttu","kutsumanimi":"Remix","tittelit":"","virallinenNimi":"Redefined Ascending Remix","rekisterinumero":"25546","syntymaaika":"4.3.2021","ika":"3 v 3 kk 17 pv","ohjaaja":"Max Sprinz","lisenssi":"","seuralyhenne":"","seuranimi":"","joukkue":"","joukkuelyhenne":"","tuloksia":0,"jaljella":"","ihanneaika":"49","enimmaisaika":"74","tavoiteaika":"","suoritusaika":"","nopeus":"","aikavirhe":"","ratavirhe":"","perusvirheita":"","kieltovirheita":0,"pisteet1":"","pisteet2":"","pisteet3":"","pisteet4":"","pisteet5":"","pisteet6":"","pisteet7":"","jokeri":"","miniGamble":"","gamble":"","summa":"","pisteet":"","tulos":"HYL","sijoitus":"","muuta":"","naytaMuuta":"","luotu":"2024-06-18T10:42:47.261+0300","riviMuokattu":"2024-06-21T14:22:10.744+0300","tulosMuokattu":"2024-06-21T14:22:10.729+0300"},{"id":275,"indeksi":45,"numero":"474","joukkuenumero":"","jasennumero":"","rotukoodi":"293","rotulyhenne":"auskel","rotunimi":"australiankelpie","sukupuoli":"uros","kutsumanimi":"Kina","tittelit":"","virallinenNimi":"NALLIKALLION KINAHMI","rekisterinumero":"ER51238/20","syntymaaika":"12.9.2020","ika":"3 v 9 kk 9 pv","ohjaaja":"Inka Mustonen","lisenssi":"60214178","seuralyhenne":"JoA","seuranimi":"JOENSUUN AGILITYURHEILIJAT","joukkue":"","joukkuelyhenne":"","tuloksia":0,"jaljella":"","ihanneaika":"49","enimmaisaika":"74","tavoiteaika":"","suoritusaika":"","nopeus":"","aikavirhe":"","ratavirhe":"","perusvirheita":"","kieltovirheita":0,"pisteet1":"","pisteet2":"","pisteet3":"","pisteet4":"","pisteet5":"","pisteet6":"","pisteet7":"","jokeri":"","miniGamble":"","gamble":"","summa":"","pisteet":"","tulos":"HYL","sijoitus":"","muuta":"","naytaMuuta":"","luotu":"2024-06-18T10:42:47.277+0300","riviMuokattu":"2024-06-21T14:23:43.503+0300","tulosMuokattu":"2024-06-21T14:23:43.499+0300"},{"id":278,"indeksi":45,"numero":"477","joukkuenumero":"","jasennumero":"","rotukoodi":"293","rotulyhenne":"auskel","rotunimi":"australiankelpie","sukupuoli":"uros","kutsumanimi":"Pepe","tittelit":"","virallinenNimi":"DUTCH DYNAMITE DAZZLER DAZ","rekisterinumero":"ER12514/17","syntymaaika":"14.7.2016","ika":"7 v 11 kk 7 pv","ohjaaja":"Tanja Kostamo","lisenssi":"40414262","seuralyhenne":"JoA","seuranimi":"JOENSUUN AGILITYURHEILIJAT","joukkue":"","joukkuelyhenne":"","tuloksia":0,"jaljella":"","ihanneaika":"49","enimmaisaika":"74","tavoiteaika":"","suoritusaika":"","nopeus":"","aikavirhe":"","ratavirhe":"","perusvirheita":"","kieltovirheita":0,"pisteet1":"","pisteet2":"","pisteet3":"","pisteet4":"","pisteet5":"","pisteet6":"","pisteet7":"","jokeri":"","miniGamble":"","gamble":"","summa":"","pisteet":"","tulos":"HYL","sijoitus":"","muuta":"","naytaMuuta":"","luotu":"2024-06-18T10:42:47.277+0300","riviMuokattu":"2024-06-21T14:45:58.610+0300","tulosMuokattu":"2024-06-21T14:45:58.610+0300"},{"id":310,"indeksi":45,"numero":"479","joukkuenumero":"","jasennumero":"","rotukoodi":"297","rotulyhenne":"borcol","rotunimi":"bordercollie","sukupuoli":"uros","kutsumanimi":"Mr. Dan","tittelit":"","virallinenNimi":"WALKING DISASTER'S LOTUS ELITE","rekisterinumero":"ER13595/17","syntymaaika":"25.12.2016","ika":"7 v 5 kk 27 pv","ohjaaja":"Karoliina Mäkelä","lisenssi":"33331694","seuralyhenne":"LÄGI","seuranimi":"LÄNSI-UUDENMAAN AGILITYHARRASTAJAT","joukkue":"","joukkuelyhenne":"","tuloksia":0,"jaljella":"","ihanneaika":"49","enimmaisaika":"74","tavoiteaika":"","suoritusaika":"","nopeus":"","aikavirhe":"","ratavirhe":"","perusvirheita":"","kieltovirheita":0,"pisteet1":"","pisteet2":"","pisteet3":"","pisteet4":"","pisteet5":"","pisteet6":"","pisteet7":"","jokeri":"","miniGamble":"","gamble":"","summa":"","pisteet":"","tulos":"HYL","sijoitus":"","muuta":"","naytaMuuta":"","luotu":"2024-06-18T10:42:47.324+0300","riviMuokattu":"2024-06-21T14:31:22.903+0300","tulosMuokattu":"2024-06-21T14:31:22.903+0300"},{"id":308,"indeksi":45,"numero":"481","joukkuenumero":"","jasennumero":"","rotukoodi":"297","rotulyhenne":"borcol","rotunimi":"bordercollie","sukupuoli":"uros","kutsumanimi":"Don","tittelit":"","virallinenNimi":"KVARKIN BRAVEHEART","rekisterinumero":"ER24164/20","syntymaaika":"20.3.2020","ika":"4 v 3 kk 1 pv","ohjaaja":"Maarit Parkkinen","lisenssi":"40430876","seuralyhenne":"LÄGI","seuranimi":"LÄNSI-UUDENMAAN AGILITYHARRASTAJAT","joukkue":"","joukkuelyhenne":"","tuloksia":0,"jaljella":"","ihanneaika":"49","enimmaisaika":"74","tavoiteaika":"","suoritusaika":"","nopeus":"","aikavirhe":"","ratavirhe":"","perusvirheita":1,"kieltovirheita":0,"pisteet1":"","pisteet2":"","pisteet3":"","pisteet4":"","pisteet5":"","pisteet6":"","pisteet7":"","jokeri":"","miniGamble":"","gamble":"","summa":"","pisteet":"","tulos":"HYL","sijoitus":"","muuta":"","naytaMuuta":"","luotu":"2024-06-18T10:42:47.308+0300","riviMuokattu":"2024-06-21T14:33:43.684+0300","tulosMuokattu":"2024-06-21T14:33:43.681+0300"},{"id":269,"indeksi":45,"numero":"482","joukkuenumero":"","jasennumero":"","rotukoodi":"342","rotulyhenne":"auspai","rotunimi":"australianpaimenkoira","sukupuoli":"narttu","kutsumanimi":"Nasu","tittelit":"","virallinenNimi":"DRAGONFLAME'S IT TAKES TWO TO TANGO","rekisterinumero":"FI12918/21","syntymaaika":"12.12.2020","ika":"3 v 6 kk 9 pv","ohjaaja":"Viivi Luuri","lisenssi":"40079441","seuralyhenne":"JAT","seuranimi":"JYVÄSKYLÄN AGILITY TEAM RY","joukkue":"","joukkuelyhenne":"","tuloksia":0,"jaljella":"","ihanneaika":"49","enimmaisaika":"74","tavoiteaika":"","suoritusaika":"","nopeus":"","aikavirhe":"","ratavirhe":"","perusvirheita":"","kieltovirheita":0,"pisteet1":"","pisteet2":"","pisteet3":"","pisteet4":"","pisteet5":"","pisteet6":"","pisteet7":"","jokeri":"","miniGamble":"","gamble":"","summa":"","pisteet":"","tulos":"HYL","sijoitus":"","muuta":"","naytaMuuta":"","luotu":"2024-06-18T10:42:47.273+0300","riviMuokattu":"2024-06-21T14:35:23.931+0300","tulosMuokattu":"2024-06-21T14:35:23.931+0300"},{"id":292,"indeksi":45,"numero":"483","joukkuenumero":"","jasennumero":"","rotukoodi":"297","rotulyhenne":"borcol","rotunimi":"bordercollie","sukupuoli":"uros","kutsumanimi":"Flit","tittelit":"","virallinenNimi":"AGILE FLIT TRUE STORY","rekisterinumero":"ER44411/19","syntymaaika":"10.11.2018","ika":"5 v 7 kk 11 pv","ohjaaja":"Pasi Partanen","lisenssi":"26790527","seuralyhenne":"E-HKK","seuranimi":"ETELÄ-HÄMEEN KOIRAKERHO RY","joukkue":"","joukkuelyhenne":"","tuloksia":0,"jaljella":"","ihanneaika":"49","enimmaisaika":"74","tavoiteaika":"","suoritusaika":"","nopeus":"","aikavirhe":"","ratavirhe":"","perusvirheita":"","kieltovirheita":0,"pisteet1":"","pisteet2":"","pisteet3":"","pisteet4":"","pisteet5":"","pisteet6":"","pisteet7":"","jokeri":"","miniGamble":"","gamble":"","summa":"","pisteet":"","tulos":"POIS","sijoitus":"","muuta":"","naytaMuuta":"","luotu":"2024-06-18T10:42:47.292+0300","riviMuokattu":"2024-06-21T08:47:08.179+0300","tulosMuokattu":"2024-06-20T00:16:55.557+0300"},{"id":268,"indeksi":45,"numero":"484","joukkuenumero":"","jasennumero":"","rotukoodi":"297","rotulyhenne":"borcol","rotunimi":"bordercollie","sukupuoli":"narttu","kutsumanimi":"Harpy","tittelit":"","virallinenNimi":"Fairfarren Fire And Forget","rekisterinumero":"DN684012302","syntymaaika":"18.5.2021","ika":"3 v 1 kk 3 pv","ohjaaja":"Soshana Dos","lisenssi":"","seuralyhenne":"","seuranimi":"","joukkue":"","joukkuelyhenne":"","tuloksia":0,"jaljella":"","ihanneaika":"49","enimmaisaika":"74","tavoiteaika":"","suoritusaika":"","nopeus":"","aikavirhe":"","ratavirhe":"","perusvirheita":"","kieltovirheita":0,"pisteet1":"","pisteet2":"","pisteet3":"","pisteet4":"","pisteet5":"","pisteet6":"","pisteet7":"","jokeri":"","miniGamble":"","gamble":"","summa":"","pisteet":"","tulos":"HYL","sijoitus":"","muuta":"","naytaMuuta":"","luotu":"2024-06-18T10:42:47.261+0300","riviMuokattu":"2024-06-21T14:36:38.800+0300","tulosMuokattu":"2024-06-21T14:36:38.800+0300"},{"id":260,"indeksi":45,"numero":"486","joukkuenumero":"","jasennumero":"","rotukoodi":"297","rotulyhenne":"borcol","rotunimi":"bordercollie","sukupuoli":"narttu","kutsumanimi":"Makkis","tittelit":"","virallinenNimi":"MITHRANDIR FLAMES","rekisterinumero":"FI16397/20","syntymaaika":"20.1.2020","ika":"4 v 5 kk 1 pv","ohjaaja":"Fiia Filander","lisenssi":"30998959","seuralyhenne":"LAU","seuranimi":"LAPPEENRANNAN AGILITY URHEILIJAT RY","joukkue":"","joukkuelyhenne":"","tuloksia":0,"jaljella":"","ihanneaika":"49","enimmaisaika":"74","tavoiteaika":"","suoritusaika":"","nopeus":"","aikavirhe":"","ratavirhe":"","perusvirheita":"","kieltovirheita":0,"pisteet1":"","pisteet2":"","pisteet3":"","pisteet4":"","pisteet5":"","pisteet6":"","pisteet7":"","jokeri":"","miniGamble":"","gamble":"","summa":"","pisteet":"","tulos":"HYL","sijoitus":"","muuta":"","naytaMuuta":"","luotu":"2024-06-18T10:42:47.245+0300","riviMuokattu":"2024-06-21T14:38:03.502+0300","tulosMuokattu":"2024-06-21T14:38:03.502+0300"},{"id":272,"indeksi":45,"numero":"488","joukkuenumero":"","jasennumero":"","rotukoodi":"277","rotulyhenne":"kroati","rotunimi":"kroatianpaimenkoira","sukupuoli":"narttu","kutsumanimi":"π","tittelit":"","virallinenNimi":"TUUS PUOLIVALSSI","rekisterinumero":"FI14816/19","syntymaaika":"30.12.2018","ika":"5 v 5 kk 22 pv","ohjaaja":"Tommi Raita-aho","lisenssi":"32261516","seuralyhenne":"TAMSK","seuranimi":"TAMPEREEN SEUDUN KOIRAKERHO R.Y.","joukkue":"","joukkuelyhenne":"","tuloksia":0,"jaljella":"","ihanneaika":"49","enimmaisaika":"74","tavoiteaika":"","suoritusaika":"","nopeus":"","aikavirhe":"","ratavirhe":"","perusvirheita":"","kieltovirheita":0,"pisteet1":"","pisteet2":"","pisteet3":"","pisteet4":"","pisteet5":"","pisteet6":"","pisteet7":"","jokeri":"","miniGamble":"","gamble":"","summa":"","pisteet":"","tulos":"HYL","sijoitus":"","muuta":"","naytaMuuta":"","luotu":"2024-06-18T10:42:47.273+0300","riviMuokattu":"2024-06-21T14:40:46.816+0300","tulosMuokattu":"2024-06-21T14:40:46.814+0300"},{"id":259,"indeksi":45,"numero":"489","joukkuenumero":"","jasennumero":"","rotukoodi":"297","rotulyhenne":"borcol","rotunimi":"bordercollie","sukupuoli":"narttu","kutsumanimi":"Nova","tittelit":"","virallinenNimi":"WALKING DISASTER'S QUARTERBACK","rekisterinumero":"FI32827/21","syntymaaika":"1.5.2021","ika":"3 v 1 kk 20 pv","ohjaaja":"Joona Sumela","lisenssi":"27084672","seuralyhenne":"PORSK","seuranimi":"PORVOONSEUDUN KOIRAHARRASTAJAT RY","joukkue":"","joukkuelyhenne":"","tuloksia":0,"jaljella":"","ihanneaika":"49","enimmaisaika":"74","tavoiteaika":"","suoritusaika":"","nopeus":"","aikavirhe":"","ratavirhe":"","perusvirheita":"","kieltovirheita":0,"pisteet1":"","pisteet2":"","pisteet3":"","pisteet4":"","pisteet5":"","pisteet6":"","pisteet7":"","jokeri":"","miniGamble":"","gamble":"","summa":"","pisteet":"","tulos":"HYL","sijoitus":"","muuta":"","naytaMuuta":"","luotu":"2024-06-18T10:42:47.245+0300","riviMuokattu":"2024-06-21T14:41:48.902+0300","tulosMuokattu":"2024-06-21T14:41:48.898+0300"},{"id":265,"indeksi":45,"numero":"490","joukkuenumero":"","jasennumero":"","rotukoodi":"297","rotulyhenne":"borcol","rotunimi":"bordercollie","sukupuoli":"narttu","kutsumanimi":"Snygi","tittelit":"","virallinenNimi":"SUPRAVULPES SNYGI","rekisterinumero":"FI16465/22","syntymaaika":"18.1.2022","ika":"2 v 5 kk 3 pv","ohjaaja":"Raisa Vähätalo","lisenssi":"32095821","seuralyhenne":"JAU","seuranimi":"JÄRVENPÄÄN AGILITYURHEILIJAT RY","joukkue":"","joukkuelyhenne":"","tuloksia":0,"jaljella":"","ihanneaika":"49","enimmaisaika":"74","tavoiteaika":"","suoritusaika":"","nopeus":"","aikavirhe":"","ratavirhe":"","perusvirheita":"","kieltovirheita":0,"pisteet1":"","pisteet2":"","pisteet3":"","pisteet4":"","pisteet5":"","pisteet6":"","pisteet7":"","jokeri":"","miniGamble":"","gamble":"","summa":"","pisteet":"","tulos":"HYL","sijoitus":"","muuta":"","naytaMuuta":"","luotu":"2024-06-18T10:42:47.261+0300","riviMuokattu":"2024-06-21T14:43:14.808+0300","tulosMuokattu":"2024-06-21T14:43:14.808+0300"},{"id":284,"indeksi":45,"numero":"491","joukkuenumero":"","jasennumero":"","rotukoodi":"297","rotulyhenne":"borcol","rotunimi":"bordercollie","sukupuoli":"uros","kutsumanimi":"Sälli","tittelit":"","virallinenNimi":"SAUNAJAAKON KILIMANJARO","rekisterinumero":"ER13175/22","syntymaaika":"17.12.2021","ika":"2 v 6 kk 4 pv","ohjaaja":"Erja Nimander","lisenssi":"32069925","seuralyhenne":"KOTKA","seuranimi":"KOTKAN KOIRANYSTÄVÄIN SEURA R.Y.","joukkue":"","joukkuelyhenne":"","tuloksia":0,"jaljella":"","ihanneaika":"49","enimmaisaika":"74","tavoiteaika":"","suoritusaika":"","nopeus":"","aikavirhe":"","ratavirhe":"","perusvirheita":"","kieltovirheita":0,"pisteet1":"","pisteet2":"","pisteet3":"","pisteet4":"","pisteet5":"","pisteet6":"","pisteet7":"","jokeri":"","miniGamble":"","gamble":"","summa":"","pisteet":"","tulos":"HYL","sijoitus":"","muuta":"","naytaMuuta":"","luotu":"2024-06-18T10:42:47.277+0300","riviMuokattu":"2024-06-21T14:44:20.491+0300","tulosMuokattu":"2024-06-21T14:44:20.491+0300"},{"id":297,"indeksi":45,"numero":"492","joukkuenumero":"","jasennumero":"","rotukoodi":"297","rotulyhenne":"borcol","rotunimi":"bordercollie","sukupuoli":"narttu","kutsumanimi":"Zirka","tittelit":"","virallinenNimi":"Be My Zirka from Extreme Team","rekisterinumero":"EST-04677/19","syntymaaika":"31.1.2019","ika":"5 v 4 kk 21 pv","ohjaaja":"Rita Annus","lisenssi":"","seuralyhenne":"","seuranimi":"","joukkue":"","joukkuelyhenne":"","tuloksia":0,"jaljella":"","ihanneaika":"49","enimmaisaika":"74","tavoiteaika":"","suoritusaika":"","nopeus":"","aikavirhe":"","ratavirhe":"","perusvirheita":"","kieltovirheita":0,"pisteet1":"","pisteet2":"","pisteet3":"","pisteet4":"","pisteet5":"","pisteet6":"","pisteet7":"","jokeri":"","miniGamble":"","gamble":"","summa":"","pisteet":"","tulos":"POIS","sijoitus":"","muuta":"","naytaMuuta":"","luotu":"2024-06-18T10:42:47.292+0300","riviMuokattu":"2024-06-21T14:48:29.596+0300","tulosMuokattu":"2024-06-21T14:48:29.596+0300"},{"id":246,"indeksi":45,"numero":"485","joukkuenumero":"","jasennumero":"","rotukoodi":"296","rotulyhenne":"lyhcol","rotunimi":"sileäkarvainen collie","sukupuoli":"narttu","kutsumanimi":"Ilves","tittelit":"","virallinenNimi":"ILVES","rekisterinumero":"FI26768/22","syntymaaika":"19.3.2022","ika":"2 v 3 kk 2 pv","ohjaaja":"Maria Evstigneeva","lisenssi":"60429376","seuralyhenne":"JAU","seuranimi":"JÄRVENPÄÄN AGILITYURHEILIJAT RY","joukkue":"","joukkuelyhenne":"","tuloksia":0,"jaljella":"","ihanneaika":"49","enimmaisaika":"74","tavoiteaika":"","suoritusaika":"","nopeus":"","aikavirhe":"","ratavirhe":"","perusvirheita":"","kieltovirheita":0,"pisteet1":"","pisteet2":"","pisteet3":"","pisteet4":"","pisteet5":"","pisteet6":"","pisteet7":"","jokeri":"","miniGamble":"","gamble":"","summa":"","pisteet":"","tulos":"HYL","sijoitus":"","muuta":"","naytaMuuta":"","luotu":"2024-06-18T10:42:47.229+0300","riviMuokattu":"2024-06-21T14:48:06.905+0300","tulosMuokattu":"2024-06-21T14:48:06.905+0300"}],"viimeisimmat_tulokset":[{"id":295,"indeksi":50,"numero":"472","joukkuenumero":"","jasennumero":"","rotukoodi":"297","rotulyhenne":"borcol","rotunimi":"bordercollie","sukupuoli":"narttu","kutsumanimi":"Toki","tittelit":"","virallinenNimi":"PROMILLEN MALIBU","rekisterinumero":"FI37510/20","syntymaaika":"3.6.2020","ika":"4 v 0 kk 18 pv","ohjaaja":"Tuulia Liuhto","lisenssi":"32192601","seuralyhenne":"LAW","seuranimi":"Littoisten Agility Warriors ry","joukkue":"","joukkuelyhenne":"","tuloksia":1,"jaljella":"","ihanneaika":"49","enimmaisaika":"74","tavoiteaika":"","suoritusaika":"42,78","nopeus":"5,12","aikavirhe":"-6,22","ratavirhe":0,"perusvirheita":0,"kieltovirheita":1,"pisteet1":"","pisteet2":"","pisteet3":"","pisteet4":"","pisteet5":"","pisteet6":"","pisteet7":"","jokeri":"","miniGamble":"","gamble":"","summa":"","pisteet":"","tulos":"-6,22","sijoitus":7,"muuta":"","naytaMuuta":"","luotu":"2024-06-18T10:42:47.292+0300","riviMuokattu":"2024-06-21T15:11:14.195+0300","tulosMuokattu":"2024-06-21T15:11:14.180+0300"},{"id":246,"indeksi":70,"numero":"485","joukkuenumero":"","jasennumero":"","rotukoodi":"296","rotulyhenne":"lyhcol","rotunimi":"sileäkarvainen collie","sukupuoli":"narttu","kutsumanimi":"Ilves","tittelit":"","virallinenNimi":"ILVES","rekisterinumero":"FI26768/22","syntymaaika":"19.3.2022","ika":"2 v 3 kk 2 pv","ohjaaja":"Maria Evstigneeva","lisenssi":"60429376","seuralyhenne":"JAU","seuranimi":"JÄRVENPÄÄN AGILITYURHEILIJAT RY","joukkue":"","joukkuelyhenne":"","tuloksia":0,"jaljella":"","ihanneaika":"49","enimmaisaika":"74","tavoiteaika":"","suoritusaika":"","nopeus":"","aikavirhe":"","ratavirhe":"","perusvirheita":"","kieltovirheita":0,"pisteet1":"","pisteet2":"","pisteet3":"","pisteet4":"","pisteet5":"","pisteet6":"","pisteet7":"","jokeri":"","miniGamble":"","gamble":"","summa":"","pisteet":"","tulos":"HYL","sijoitus":"","muuta":"","naytaMuuta":"","luotu":"2024-06-18T10:42:47.229+0300","riviMuokattu":"2024-06-21T14:48:06.905+0300","tulosMuokattu":"2024-06-21T14:48:06.905+0300"},{"id":278,"indeksi":55,"numero":"477","joukkuenumero":"","jasennumero":"","rotukoodi":"293","rotulyhenne":"auskel","rotunimi":"australiankelpie","sukupuoli":"uros","kutsumanimi":"Pepe","tittelit":"","virallinenNimi":"DUTCH DYNAMITE DAZZLER DAZ","rekisterinumero":"ER12514/17","syntymaaika":"14.7.2016","ika":"7 v 11 kk 7 pv","ohjaaja":"Tanja Kostamo","lisenssi":"40414262","seuralyhenne":"JoA","seuranimi":"JOENSUUN AGILITYURHEILIJAT","joukkue":"","joukkuelyhenne":"","tuloksia":0,"jaljella":"","ihanneaika":"49","enimmaisaika":"74","tavoiteaika":"","suoritusaika":"","nopeus":"","aikavirhe":"","ratavirhe":"","perusvirheita":"","kieltovirheita":0,"pisteet1":"","pisteet2":"","pisteet3":"","pisteet4":"","pisteet5":"","pisteet6":"","pisteet7":"","jokeri":"","miniGamble":"","gamble":"","summa":"","pisteet":"","tulos":"HYL","sijoitus":"","muuta":"","naytaMuuta":"","luotu":"2024-06-18T10:42:47.277+0300","riviMuokattu":"2024-06-21T14:45:58.610+0300","tulosMuokattu":"2024-06-21T14:45:58.610+0300"},{"id":284,"indeksi":68,"numero":"491","joukkuenumero":"","jasennumero":"","rotukoodi":"297","rotulyhenne":"borcol","rotunimi":"bordercollie","sukupuoli":"uros","kutsumanimi":"Sälli","tittelit":"","virallinenNimi":"SAUNAJAAKON KILIMANJARO","rekisterinumero":"ER13175/22","syntymaaika":"17.12.2021","ika":"2 v 6 kk 4 pv","ohjaaja":"Erja Nimander","lisenssi":"32069925","seuralyhenne":"KOTKA","seuranimi":"KOTKAN KOIRANYSTÄVÄIN SEURA R.Y.","joukkue":"","joukkuelyhenne":"","tuloksia":0,"jaljella":"","ihanneaika":"49","enimmaisaika":"74","tavoiteaika":"","suoritusaika":"","nopeus":"","aikavirhe":"","ratavirhe":"","perusvirheita":"","kieltovirheita":0,"pisteet1":"","pisteet2":"","pisteet3":"","pisteet4":"","pisteet5":"","pisteet6":"","pisteet7":"","jokeri":"","miniGamble":"","gamble":"","summa":"","pisteet":"","tulos":"HYL","sijoitus":"","muuta":"","naytaMuuta":"","luotu":"2024-06-18T10:42:47.277+0300","riviMuokattu":"2024-06-21T14:44:20.491+0300","tulosMuokattu":"2024-06-21T14:44:20.491+0300"},{"id":265,"indeksi":67,"numero":"490","joukkuenumero":"","jasennumero":"","rotukoodi":"297","rotulyhenne":"borcol","rotunimi":"bordercollie","sukupuoli":"narttu","kutsumanimi":"Snygi","tittelit":"","virallinenNimi":"SUPRAVULPES SNYGI","rekisterinumero":"FI16465/22","syntymaaika":"18.1.2022","ika":"2 v 5 kk 3 pv","ohjaaja":"Raisa Vähätalo","lisenssi":"32095821","seuralyhenne":"JAU","seuranimi":"JÄRVENPÄÄN AGILITYURHEILIJAT RY","joukkue":"","joukkuelyhenne":"","tuloksia":0,"jaljella":"","ihanneaika":"49","enimmaisaika":"74","tavoiteaika":"","suoritusaika":"","nopeus":"","aikavirhe":"","ratavirhe":"","perusvirheita":"","kieltovirheita":0,"pisteet1":"","pisteet2":"","pisteet3":"","pisteet4":"","pisteet5":"","pisteet6":"","pisteet7":"","jokeri":"","miniGamble":"","gamble":"","summa":"","pisteet":"","tulos":"HYL","sijoitus":"","muuta":"","naytaMuuta":"","luotu":"2024-06-18T10:42:47.261+0300","riviMuokattu":"2024-06-21T14:43:14.808+0300","tulosMuokattu":"2024-06-21T14:43:14.808+0300"}],"poistettu":"0","muokattu":"2024-06-26 22:01:29","omistaja":false}