{"paiva":"2024-06-23","jarjestaja_id":"-306421049","jarjestaja_nimi":"Agility Festivals ry","kilpailu_id":"-1441380992","kilpailu_kuvaus":"F agilityrata","kilpailu_tyyppi":"1","luokka_koodi":"M1","luokka_kuvaus":"Medi 1","indeksi":"18","koirakoita":"5","jaljella":"0","ihanneaika":"47","enimmaisaika":"71","pituus":"170","aloitusaika":"10:00","tuomari":"Petr Pup\u00edk (Tsekki)","tulokset":[{"id":13,"indeksi":18,"numero":"49","joukkuenumero":"","jasennumero":"","rotukoodi":"","rotulyhenne":"","rotunimi":"","sukupuoli":"narttu","kutsumanimi":"Mytty","tittelit":"","virallinenNimi":"LOVELY LION I'M MOVING UP AND DOWN","rekisterinumero":"ER59440/21","syntymaaika":"21.10.2021","ika":"2 v 8 kk 2 pv","ohjaaja":"Tanja Kurikka","lisenssi":"22193348","seuralyhenne":"YLÖKK","seuranimi":"YLÖJÄRVEN KOIRAKERHO RY","joukkue":"","joukkuelyhenne":"","tuloksia":1,"jaljella":"","ihanneaika":"47","enimmaisaika":"71","tavoiteaika":"","suoritusaika":"46,58","nopeus":"3,65","aikavirhe":"-0,42","ratavirhe":15,"perusvirheita":1,"kieltovirheita":1,"pisteet1":"","pisteet2":"","pisteet3":"","pisteet4":"","pisteet5":"","pisteet6":"","pisteet7":"","jokeri":"","miniGamble":"","gamble":"","summa":"","pisteet":"","tulos":"15","sijoitus":1,"muuta":"","naytaMuuta":"","luotu":"2024-06-18T10:42:47.860+0300","riviMuokattu":"2024-06-23T10:22:35.319+0300","tulosMuokattu":"2024-06-23T10:22:35.319+0300"},{"id":20,"indeksi":18,"numero":"44","joukkuenumero":"","jasennumero":"","rotukoodi":"999","rotulyhenne":"x-rotu","rotunimi":"sekarotuinen","sukupuoli":"uros","kutsumanimi":"Onni","tittelit":"","virallinenNimi":"-","rekisterinumero":"-","syntymaaika":"31.5.2011","ika":"13 v 0 kk 23 pv","ohjaaja":"Carmen Miller","lisenssi":"","seuralyhenne":"","seuranimi":"","joukkue":"","joukkuelyhenne":"","tuloksia":0,"jaljella":"","ihanneaika":"47","enimmaisaika":"71","tavoiteaika":"","suoritusaika":"","nopeus":"","aikavirhe":"","ratavirhe":"","perusvirheita":"","kieltovirheita":0,"pisteet1":"","pisteet2":"","pisteet3":"","pisteet4":"","pisteet5":"","pisteet6":"","pisteet7":"","jokeri":"","miniGamble":"","gamble":"","summa":"","pisteet":"","tulos":"POIS","sijoitus":"","muuta":"","naytaMuuta":"","luotu":"2024-06-18T10:42:47.873+0300","riviMuokattu":"2024-06-23T10:29:19.768+0300","tulosMuokattu":"2024-06-23T10:29:19.768+0300"},{"id":12,"indeksi":18,"numero":"51","joukkuenumero":"","jasennumero":"","rotukoodi":"5","rotulyhenne":"cocspa","rotunimi":"cockerspanieli","sukupuoli":"uros","kutsumanimi":"Wix","tittelit":"","virallinenNimi":"LAHJAKAS NANNAANANANA","rekisterinumero":"FI60666/21","syntymaaika":"29.10.2021","ika":"2 v 7 kk 25 pv","ohjaaja":"Erica Nykvist","lisenssi":"28994978","seuralyhenne":"TSAU","seuranimi":"TURUN SEUDUN AGILITYURHEILIJAT RY","joukkue":"","joukkuelyhenne":"","tuloksia":0,"jaljella":"","ihanneaika":"47","enimmaisaika":"71","tavoiteaika":"","suoritusaika":"","nopeus":"","aikavirhe":"","ratavirhe":"","perusvirheita":"","kieltovirheita":0,"pisteet1":"","pisteet2":"","pisteet3":"","pisteet4":"","pisteet5":"","pisteet6":"","pisteet7":"","jokeri":"","miniGamble":"","gamble":"","summa":"","pisteet":"","tulos":"HYL","sijoitus":"","muuta":"","naytaMuuta":"","luotu":"2024-06-18T10:42:47.860+0300","riviMuokattu":"2024-06-23T10:24:55.660+0300","tulosMuokattu":"2024-06-23T10:24:55.658+0300"},{"id":15,"indeksi":18,"numero":"55","joukkuenumero":"","jasennumero":"","rotukoodi":"138","rotulyhenne":"pyrpal","rotunimi":"lyhytkarvainen pyreneittenpaimenkoira","sukupuoli":"uros","kutsumanimi":"Noah","tittelit":"","virallinenNimi":"O'OU REBELLIOUS ROADRUNNER","rekisterinumero":"Fi53871/20","syntymaaika":"18.9.2020","ika":"3 v 9 kk 5 pv","ohjaaja":"Taina Rantanen","lisenssi":"40078050","seuralyhenne":"VEKORA","seuranimi":"Veikkolan Koirakerho ry","joukkue":"","joukkuelyhenne":"","tuloksia":0,"jaljella":"","ihanneaika":"47","enimmaisaika":"71","tavoiteaika":"","suoritusaika":"","nopeus":"","aikavirhe":"","ratavirhe":"","perusvirheita":"","kieltovirheita":0,"pisteet1":"","pisteet2":"","pisteet3":"","pisteet4":"","pisteet5":"","pisteet6":"","pisteet7":"","jokeri":"","miniGamble":"","gamble":"","summa":"","pisteet":"","tulos":"HYL","sijoitus":"","muuta":"","naytaMuuta":"","luotu":"2024-06-18T10:42:47.860+0300","riviMuokattu":"2024-06-23T10:26:35.132+0300","tulosMuokattu":"2024-06-23T10:26:35.132+0300"},{"id":18,"indeksi":18,"numero":"60","joukkuenumero":"","jasennumero":"","rotukoodi":"5","rotulyhenne":"cocspa","rotunimi":"cockerspanieli","sukupuoli":"uros","kutsumanimi":"Hatsipurilainen","tittelit":"","virallinenNimi":"LAHJAKAS OMINTAKEINEN","rekisterinumero":"FI52266/22","syntymaaika":"17.9.2022","ika":"1 v 9 kk 6 pv","ohjaaja":"Katja Virtanen","lisenssi":"29703485","seuralyhenne":"KIRSUT","seuranimi":"LOHJAN KIRSUT RY","joukkue":"","joukkuelyhenne":"","tuloksia":0,"jaljella":"","ihanneaika":"47","enimmaisaika":"71","tavoiteaika":"","suoritusaika":"","nopeus":"","aikavirhe":"","ratavirhe":"","perusvirheita":"","kieltovirheita":0,"pisteet1":"","pisteet2":"","pisteet3":"","pisteet4":"","pisteet5":"","pisteet6":"","pisteet7":"","jokeri":"","miniGamble":"","gamble":"","summa":"","pisteet":"","tulos":"HYL","sijoitus":"","muuta":"","naytaMuuta":"","luotu":"2024-06-18T10:42:47.860+0300","riviMuokattu":"2024-06-23T10:27:29.946+0300","tulosMuokattu":"2024-06-23T10:27:29.905+0300"},{"id":19,"indeksi":18,"numero":"62","joukkuenumero":"","jasennumero":"","rotukoodi":"297","rotulyhenne":"borcol","rotunimi":"bordercollie","sukupuoli":"narttu","kutsumanimi":"Vaiana","tittelit":"","virallinenNimi":"Aim High For The Stars Kissable Loveable Vaiana","rekisterinumero":"PKR.I-118457","syntymaaika":"27.5.2022","ika":"2 v 0 kk 27 pv","ohjaaja":"Kriste Kosseson","lisenssi":"","seuralyhenne":"","seuranimi":"","joukkue":"","joukkuelyhenne":"","tuloksia":0,"jaljella":"","ihanneaika":"47","enimmaisaika":"71","tavoiteaika":"","suoritusaika":"","nopeus":"","aikavirhe":"","ratavirhe":"","perusvirheita":"","kieltovirheita":0,"pisteet1":"","pisteet2":"","pisteet3":"","pisteet4":"","pisteet5":"","pisteet6":"","pisteet7":"","jokeri":"","miniGamble":"","gamble":"","summa":"","pisteet":"","tulos":"POIS","sijoitus":"","muuta":"","naytaMuuta":"","luotu":"2024-06-18T10:42:47.873+0300","riviMuokattu":"2024-06-23T10:29:23.350+0300","tulosMuokattu":"2024-06-23T10:29:23.350+0300"},{"id":11,"indeksi":18,"numero":"66","joukkuenumero":"","jasennumero":"","rotukoodi":"88","rotulyhenne":"shelam","rotunimi":"shetlanninlammaskoira","sukupuoli":"uros","kutsumanimi":"Seppo","tittelit":"","virallinenNimi":"CHILLY BREEZE CLOUDED LEOPARD","rekisterinumero":"FI40929/20","syntymaaika":"8.7.2020","ika":"3 v 11 kk 15 pv","ohjaaja":"Emma-Kaisa Ruhala","lisenssi":"40410318","seuralyhenne":"SWAU","seuranimi":"SAWON AGILITY URHEILIJAT RY","joukkue":"","joukkuelyhenne":"","tuloksia":0,"jaljella":"","ihanneaika":"47","enimmaisaika":"71","tavoiteaika":"","suoritusaika":"","nopeus":"","aikavirhe":"","ratavirhe":"","perusvirheita":"","kieltovirheita":0,"pisteet1":"","pisteet2":"","pisteet3":"","pisteet4":"","pisteet5":"","pisteet6":"","pisteet7":"","jokeri":"","miniGamble":"","gamble":"","summa":"","pisteet":"","tulos":"HYL","sijoitus":"","muuta":"","naytaMuuta":"","luotu":"2024-06-18T10:42:47.860+0300","riviMuokattu":"2024-06-23T10:29:07.558+0300","tulosMuokattu":"2024-06-23T10:29:07.558+0300"},{"id":21,"indeksi":18,"numero":"73","joukkuenumero":"","jasennumero":"","rotukoodi":"238","rotulyhenne":"mudi","rotunimi":"mudi","sukupuoli":"narttu","kutsumanimi":"Azi","tittelit":"","virallinenNimi":"Azzurra","rekisterinumero":"IKCB60795","syntymaaika":"2.11.2021","ika":"2 v 7 kk 21 pv","ohjaaja":"Magdalena Surblys","lisenssi":"","seuralyhenne":"","seuranimi":"","joukkue":"","joukkuelyhenne":"","tuloksia":0,"jaljella":"","ihanneaika":"47","enimmaisaika":"71","tavoiteaika":"","suoritusaika":"","nopeus":"","aikavirhe":"","ratavirhe":"","perusvirheita":"","kieltovirheita":0,"pisteet1":"","pisteet2":"","pisteet3":"","pisteet4":"","pisteet5":"","pisteet6":"","pisteet7":"","jokeri":"","miniGamble":"","gamble":"","summa":"","pisteet":"","tulos":"POIS","sijoitus":"","muuta":"","naytaMuuta":"","luotu":"2024-06-18T10:42:47.873+0300","riviMuokattu":"2024-06-23T10:29:15.790+0300","tulosMuokattu":"2024-06-23T10:29:15.790+0300"},{"id":22,"indeksi":18,"numero":"77","joukkuenumero":"","jasennumero":"","rotukoodi":"918","rotulyhenne":"pampai","rotunimi":"pieniamerikanpaimenkoira","sukupuoli":"uros","kutsumanimi":"Smooch","tittelit":"","virallinenNimi":"Legacy’s smooches for the audience","rekisterinumero":"EST-04321/20","syntymaaika":"12.5.2019","ika":"5 v 1 kk 11 pv","ohjaaja":"erin Dunaway","lisenssi":"","seuralyhenne":"","seuranimi":"","joukkue":"","joukkuelyhenne":"","tuloksia":0,"jaljella":"","ihanneaika":"47","enimmaisaika":"71","tavoiteaika":"","suoritusaika":"","nopeus":"","aikavirhe":"","ratavirhe":"","perusvirheita":"","kieltovirheita":0,"pisteet1":"","pisteet2":"","pisteet3":"","pisteet4":"","pisteet5":"","pisteet6":"","pisteet7":"","jokeri":"","miniGamble":"","gamble":"","summa":"","pisteet":"","tulos":"POIS","sijoitus":"","muuta":"","naytaMuuta":"","luotu":"2024-06-18T10:42:47.876+0300","riviMuokattu":"2024-06-22T01:42:34.571+0300","tulosMuokattu":"2024-06-22T01:42:34.571+0300"},{"id":68,"indeksi":18,"numero":"220","joukkuenumero":"","jasennumero":"","rotukoodi":"88","rotulyhenne":"shelam","rotunimi":"shetlanninlammaskoira","sukupuoli":"uros","kutsumanimi":"Duff","tittelit":"","virallinenNimi":"Lillstigens Daddy Cool","rekisterinumero":"FI29462/21","syntymaaika":"3.3.2021","ika":"3 v 3 kk 20 pv","ohjaaja":"Niina-Liina Linna","lisenssi":"32172676","seuralyhenne":"NAS","seuranimi":"NORTHERN AGILITY SPORT RY","joukkue":"","joukkuelyhenne":"","tuloksia":0,"jaljella":"","ihanneaika":"47","enimmaisaika":"71","tavoiteaika":"","suoritusaika":"","nopeus":"","aikavirhe":"","ratavirhe":"","perusvirheita":"","kieltovirheita":0,"pisteet1":"","pisteet2":"","pisteet3":"","pisteet4":"","pisteet5":"","pisteet6":"","pisteet7":"","jokeri":"","miniGamble":"","gamble":"","summa":"","pisteet":"","tulos":"POIS","sijoitus":"","muuta":"","naytaMuuta":"","luotu":"2024-06-18T10:42:47.924+0300","riviMuokattu":"2024-06-23T10:29:18.213+0300","tulosMuokattu":"2024-06-23T10:29:18.213+0300"}],"viimeisimmat_tulokset":[{"id":11,"indeksi":6,"numero":"66","joukkuenumero":"","jasennumero":"","rotukoodi":"88","rotulyhenne":"shelam","rotunimi":"shetlanninlammaskoira","sukupuoli":"uros","kutsumanimi":"Seppo","tittelit":"","virallinenNimi":"CHILLY BREEZE CLOUDED LEOPARD","rekisterinumero":"FI40929/20","syntymaaika":"8.7.2020","ika":"3 v 11 kk 15 pv","ohjaaja":"Emma-Kaisa Ruhala","lisenssi":"40410318","seuralyhenne":"SWAU","seuranimi":"SAWON AGILITY URHEILIJAT RY","joukkue":"","joukkuelyhenne":"","tuloksia":0,"jaljella":"","ihanneaika":"47","enimmaisaika":"71","tavoiteaika":"","suoritusaika":"","nopeus":"","aikavirhe":"","ratavirhe":"","perusvirheita":"","kieltovirheita":0,"pisteet1":"","pisteet2":"","pisteet3":"","pisteet4":"","pisteet5":"","pisteet6":"","pisteet7":"","jokeri":"","miniGamble":"","gamble":"","summa":"","pisteet":"","tulos":"HYL","sijoitus":"","muuta":"","naytaMuuta":"","luotu":"2024-06-18T10:42:47.860+0300","riviMuokattu":"2024-06-23T10:29:07.558+0300","tulosMuokattu":"2024-06-23T10:29:07.558+0300"},{"id":18,"indeksi":4,"numero":"60","joukkuenumero":"","jasennumero":"","rotukoodi":"5","rotulyhenne":"cocspa","rotunimi":"cockerspanieli","sukupuoli":"uros","kutsumanimi":"Hatsipurilainen","tittelit":"","virallinenNimi":"LAHJAKAS OMINTAKEINEN","rekisterinumero":"FI52266/22","syntymaaika":"17.9.2022","ika":"1 v 9 kk 6 pv","ohjaaja":"Katja Virtanen","lisenssi":"29703485","seuralyhenne":"KIRSUT","seuranimi":"LOHJAN KIRSUT RY","joukkue":"","joukkuelyhenne":"","tuloksia":0,"jaljella":"","ihanneaika":"47","enimmaisaika":"71","tavoiteaika":"","suoritusaika":"","nopeus":"","aikavirhe":"","ratavirhe":"","perusvirheita":"","kieltovirheita":0,"pisteet1":"","pisteet2":"","pisteet3":"","pisteet4":"","pisteet5":"","pisteet6":"","pisteet7":"","jokeri":"","miniGamble":"","gamble":"","summa":"","pisteet":"","tulos":"HYL","sijoitus":"","muuta":"","naytaMuuta":"","luotu":"2024-06-18T10:42:47.860+0300","riviMuokattu":"2024-06-23T10:27:29.946+0300","tulosMuokattu":"2024-06-23T10:27:29.905+0300"},{"id":15,"indeksi":3,"numero":"55","joukkuenumero":"","jasennumero":"","rotukoodi":"138","rotulyhenne":"pyrpal","rotunimi":"lyhytkarvainen pyreneittenpaimenkoira","sukupuoli":"uros","kutsumanimi":"Noah","tittelit":"","virallinenNimi":"O'OU REBELLIOUS ROADRUNNER","rekisterinumero":"Fi53871/20","syntymaaika":"18.9.2020","ika":"3 v 9 kk 5 pv","ohjaaja":"Taina Rantanen","lisenssi":"40078050","seuralyhenne":"VEKORA","seuranimi":"Veikkolan Koirakerho ry","joukkue":"","joukkuelyhenne":"","tuloksia":0,"jaljella":"","ihanneaika":"47","enimmaisaika":"71","tavoiteaika":"","suoritusaika":"","nopeus":"","aikavirhe":"","ratavirhe":"","perusvirheita":"","kieltovirheita":0,"pisteet1":"","pisteet2":"","pisteet3":"","pisteet4":"","pisteet5":"","pisteet6":"","pisteet7":"","jokeri":"","miniGamble":"","gamble":"","summa":"","pisteet":"","tulos":"HYL","sijoitus":"","muuta":"","naytaMuuta":"","luotu":"2024-06-18T10:42:47.860+0300","riviMuokattu":"2024-06-23T10:26:35.132+0300","tulosMuokattu":"2024-06-23T10:26:35.132+0300"},{"id":12,"indeksi":2,"numero":"51","joukkuenumero":"","jasennumero":"","rotukoodi":"5","rotulyhenne":"cocspa","rotunimi":"cockerspanieli","sukupuoli":"uros","kutsumanimi":"Wix","tittelit":"","virallinenNimi":"LAHJAKAS NANNAANANANA","rekisterinumero":"FI60666/21","syntymaaika":"29.10.2021","ika":"2 v 7 kk 25 pv","ohjaaja":"Erica Nykvist","lisenssi":"28994978","seuralyhenne":"TSAU","seuranimi":"TURUN SEUDUN AGILITYURHEILIJAT RY","joukkue":"","joukkuelyhenne":"","tuloksia":0,"jaljella":"","ihanneaika":"47","enimmaisaika":"71","tavoiteaika":"","suoritusaika":"","nopeus":"","aikavirhe":"","ratavirhe":"","perusvirheita":"","kieltovirheita":0,"pisteet1":"","pisteet2":"","pisteet3":"","pisteet4":"","pisteet5":"","pisteet6":"","pisteet7":"","jokeri":"","miniGamble":"","gamble":"","summa":"","pisteet":"","tulos":"HYL","sijoitus":"","muuta":"","naytaMuuta":"","luotu":"2024-06-18T10:42:47.860+0300","riviMuokattu":"2024-06-23T10:24:55.660+0300","tulosMuokattu":"2024-06-23T10:24:55.658+0300"},{"id":13,"indeksi":1,"numero":"49","joukkuenumero":"","jasennumero":"","rotukoodi":"","rotulyhenne":"","rotunimi":"","sukupuoli":"narttu","kutsumanimi":"Mytty","tittelit":"","virallinenNimi":"LOVELY LION I'M MOVING UP AND DOWN","rekisterinumero":"ER59440/21","syntymaaika":"21.10.2021","ika":"2 v 8 kk 2 pv","ohjaaja":"Tanja Kurikka","lisenssi":"22193348","seuralyhenne":"YLÖKK","seuranimi":"YLÖJÄRVEN KOIRAKERHO RY","joukkue":"","joukkuelyhenne":"","tuloksia":1,"jaljella":"","ihanneaika":"47","enimmaisaika":"71","tavoiteaika":"","suoritusaika":"46,58","nopeus":"3,65","aikavirhe":"-0,42","ratavirhe":15,"perusvirheita":1,"kieltovirheita":1,"pisteet1":"","pisteet2":"","pisteet3":"","pisteet4":"","pisteet5":"","pisteet6":"","pisteet7":"","jokeri":"","miniGamble":"","gamble":"","summa":"","pisteet":"","tulos":"15","sijoitus":1,"muuta":"","naytaMuuta":"","luotu":"2024-06-18T10:42:47.860+0300","riviMuokattu":"2024-06-23T10:22:35.319+0300","tulosMuokattu":"2024-06-23T10:22:35.319+0300"}],"poistettu":"0","muokattu":"2024-06-26 22:23:34","omistaja":false}